Workbook
Name afsfasfad: '[1]Coleta de Dados'!#REF!
Name afsfasfad: '[2]Coleta de Dados'!#REF!
Name afsfasfad: '[2]Coleta de Dados'!#REF!
Name Cabine15: '[1]Coleta de Dados'!$BF$7:$BF$1129
Name Cabine15: '[2]Coleta de Dados'!$BF$7:$BF$1129
Name Cabine32: '[1]Coleta de Dados'!$BL$7:$BL$1129
Name Cabine32: '[2]Coleta de Dados'!$BL$7:$BL$1129
Name Cabine85: '[1]Coleta de Dados'!$BG$7:$BG$1129
Name Cabine85: '[2]Coleta de Dados'!$BG$7:$BG$1129
Name CentrosdeCustos: [1]Consulta!$A$2:$E$30
Name CentrosdeCustos: [2]Consulta!$A$2:$E$30
Name Compressores: '[1]Coleta de Dados'!$BR$7:$BR$1129
Name Compressores: '[2]Coleta de Dados'!$BR$7:$BR$1129
Name Dados: '[1]Coleta de Dados'!$C$7:$Y$1129
Name Dados: '[2]Coleta de Dados'!$C$7:$Y$1129
Name DataTérmino: '[1]Coleta de Dados'!$W$7:$W$1129
Name DataTérmino: '[2]Coleta de Dados'!$W$7:$W$1129
Name DimecoConectores: '[1]Coleta de Dados'!$BV$7:$BV$1129
Name DimecoConectores: '[2]Coleta de Dados'!$BV$7:$BV$1129
Name DimecoTravesanos: '[1]Coleta de Dados'!$BI$7:$BI$1129
Name DimecoTravesanos: '[2]Coleta de Dados'!$BI$7:$BI$1129
Name DobradeiraSorg: '[1]Coleta de Dados'!$BU$7:$BU$1129
Name DobradeiraSorg: '[2]Coleta de Dados'!$BU$7:$BU$1129
Name Emissão: '[1]Coleta de Dados'!$AD$1:$AD$65536
Name Emissão: '[2]Coleta de Dados'!$AD$1:$AD$65536
Name Empilhadeiraelet: '[1]Coleta de Dados'!$CC$7:$CC$1129
Name Empilhadeiraelet: '[2]Coleta de Dados'!$CC$7:$CC$1129
Name Entradas: '[1]Coleta de Dados'!$F$7:$F$1129
Name Entradas: '[2]Coleta de Dados'!$F$7:$F$1129
Name Equipamentos: '[1]Coleta de Dados'!$H$7:$H$1129
Name Equipamentos: '[2]Coleta de Dados'!$H$7:$H$1129
Name Esmerilhadeira: '[1]Coleta de Dados'!$CD$7:$CD$1129
Name Esmerilhadeira: '[2]Coleta de Dados'!$CD$7:$CD$1129
Name FagorLargueros: '[1]Coleta de Dados'!$BM$7:$BM$1129
Name FagorLargueros: '[2]Coleta de Dados'!$BM$7:$BM$1129
Name FagorMontantes: '[1]Coleta de Dados'!$BJ$7:$BJ$1129
Name FagorMontantes: '[2]Coleta de Dados'!$BJ$7:$BJ$1129
Name Fresadora: '[1]Coleta de Dados'!$BT$7:$BT$1129
Name Fresadora: '[2]Coleta de Dados'!$BT$7:$BT$1129
Name FuradeiraColuna: '[1]Coleta de Dados'!$BS$7:$BS$1129
Name FuradeiraColuna: '[2]Coleta de Dados'!$BS$7:$BS$1129
Name Gasparini: '[1]Coleta de Dados'!$BN$7:$BN$1129
Name Gasparini: '[2]Coleta de Dados'!$BN$7:$BN$1129
Name GuilhotinaSorg: '[1]Coleta de Dados'!$BK$7:$BK$1129
Name GuilhotinaSorg: '[2]Coleta de Dados'!$BK$7:$BK$1129
Name imp: '[1]Coleta de Dados'!#REF!
Name imp: '[2]Coleta de Dados'!#REF!
Name imp: '[2]Coleta de Dados'!#REF!
Name Impressora: '[1]Coleta de Dados'!#REF!
Name Impressora: '[2]Coleta de Dados'!#REF!
Name Impressora: '[2]Coleta de Dados'!#REF!
Name LUIS: '[1]Coleta de Dados'!#REF!
Name LUIS: '[2]Coleta de Dados'!#REF!
Name MáqEmbalar: '[1]Coleta de Dados'!$CA$7:$CA$1129
Name MáqEmbalar: '[2]Coleta de Dados'!$CA$7:$CA$1129
Name Mês: '[1]Coleta de Dados'!$AB$7:$AB$1129
Name Mês: '[2]Coleta de Dados'!$AB$7:$AB$1129
Name MêsI: '[1]Coleta de Dados'!$AB$7:$AB$1129
Name MêsI: '[2]Coleta de Dados'!$AB$7:$AB$1129
Name MêsT: '[1]Coleta de Dados'!$AC$7:$AC$1129

Sheet CLIENTES
A1: REMED MEDICAL SERVICE | B1: INSTITUCIÓN
A2: ZENTRIA AVIDANTI | B2: MEDIASISTENCIA
A3: VidaNova IPS | B3: MEDICOL
A4: VIDAMEDICAL BOGOTA IPS SAS | B4: UNIANDES
A5: VANTIVE S.A.S. | B5: MEDICADIZ
A6: VALLESALUD | B6: MARIO GAITAN YANGUAS
A7: UNIVERSIDAD PONTIFICIA BOLIVARIANA | B7: MAGILAB S.A.S
A8: UNION TEMPORAL SERVISALUD SAN JOSE | B8: MAGISTRALES DE COLOMBIA
A9: UNION TEMPORAL RED VITAL | B9: LIGA CONTRA EL CANCER DE RISARALDA
A10: UNIDHOS IPS | B10: LA CASA DEL NIÑO
A11: UNIDAD DE ORIENTACION Y ASISTENCIA MATERNA | B11: LA CARDIO
A12: UNIANDES | B12: MACROMEDICOS
... A149: BOSTON MEDICAL | B149: BIO VIE S.A.S
A150: BIO VIE S.A.S | B150: BAXTER | D150: CENTRO ORIENTE | E150: SANTA CLARA | F150: SAN BLAS | G150: MATERNO SUR | H150: VICTORIA | I150: BRAVO PAEZ
A151: BAXTER | B151: AUDIFARMA | D151: NORTE | E151: SUBA | F151: ENGATIVA | G151: SIMON BOLIVAR
A152: AUDIFARMA | B152: ANDREA PERILLA | D152: SUB RED SUR OCCIDENTE | E152: KENNEDY
A153: ANGIOGRAFÍA DE COLOMBIA S.A. | B153: ONCOLOGIA DUMIAN CLINICA MARIANGEL
A154: REMED MEDICAL SERVICE | B154: HOSPITAL MARCO FIDEL SUAREZ DE BELLO | D154: SUB RED SUR | E154: TUNAL | F154: MEISEN | G154: VISTA HERMOSA
A155: CAJA DE COMPENSACION FAMILIAR DE CALDAS | B155: PROVIDA IPS
A156: SERVIMOS CAUCA | B156: RED VITAL DEL VALLE
A157: FARMART | B157: REINA SOFIA
A158: HOSPITAL ENGATIVA SUBRED NORTE | B158: RIESGO DE FRACTURA S.A - CAYRE
A159: HOSPITAL MEISSEN -SUBRED SUR | B159: RM SUMINISTROS UT
A160: HOSPITAL SUBA SUBRED NORTE | B160: RTS AGENCIA HUV
A161: DIACOR SOACHA ZONA FRANCA S A S | B161: RTS SANTA CLARA
A162: UMHES MATERNO INFANTIL SUBRED CENTRO ORIENTE | B162: RTS AGENCIA PALMIRA
A163: HACES INVERSIONES Y SERVICIOS S.A.S. | B163: RTS AGENCIA SANTA CLARA
A164: MESSER COLOMBIA S.A. | B164: RTS AGENCIA SUCURSAL POPAYAN
A165: CLINICA CHIA S A S | B165: RTS BARRANQUILLA
A166: HOSPITAL EL TUNAL -SUBRED SUR | B166: RTS CARDIOINFANTIL
... A191: CLINICA DEL CONTRY | B191: UNIDHOS IPS
B192: UNION TEMPORAL RED VIRTAL
B193: VALLE SALUD
B194: VIDAMEICA IPS
B195: LIGA CONTRA EL CÁNCER RISARALDA
B196: INSTITUTO ONCOLÓGICO DEL GRUPO OSPEDALE. INOOS
B197: FEMSALUD
B198: E.S.E HOSPITAL UNIVERSITARIO DE LA SAMARITANA - HOSPITAL REGIONAL DE ZIPAQUIRA
B199: SAN RAFAEL DE PEREIRA
B200: Clínica Avidanti Ciudad Verde
B201: ANGIOGRAFIA DE COLOMBIA
B202: VANTIVE
B203: VidaNova IPS
... B215: FARMART
A216: m | B216: CLINICA PRIMERA DE MAYO BARRANQUILLA
A217: m | B217: COLSUBSIDIO
A218: m | B218: EMPRESA SOCIAL DEL ESTADO SANTIAGO DE TUNJA
A219: m | B219: EMSSANAR EPS
A220: m | B220: SIES SALUD
A221: m | B221: CLINICA ZENTRIA LA MILAGROSA SAS
A222: m | B222: CLINICA MAICAO NUESTRA
A223: m | B223: SURAMERICANA IPS SERVICIOS SALUD
B224: CLINICA JUAN N CORPAS
B225: AVIDANTE BUS HOSPITAL DEL NORTE
B226: HOSPITAL ALMA MATER
B227: ATENCION INTEGRAL EN CASA
B228: FARALLONES
B229: PALMA REAL
B230: HOCEN
B231: COUNTRY
B232: Hospital Susana López de Valencia
B233: CLINICA DEL CONTRY

Sheet ATENCION 
L1: Pagina 1 de 1
B2: ATENCIÓN Y SEGUIMIENTO DE PQRS | L2: CÓDIGO: AC-FR-054-04
B4: DATOS DE RECEPCIÓN DE PQRS
B6: Fecha PQRS: | E6: 46122 | F6: Regional: | G6: LLANOS | J6: Solicitud N°: | L6: 130
B9: Hora de recepción | E9: 0.78888889 | F9: Medio de la queja | H9: E-MAIL
G10: Carta, E-mail, Telefono, Web, Personal
B11: Nombre del receptor de la PQRS | F11: SERVICIO AL CLIENTE
B14: DATOS DEL SOLICITANTE
E16: CLIENTE
E17: CLINICA PRIMAVERA LLANOS
E18: INSTITUCION
E19: CLINICA PRIMAVERA LLANOS
E20: CIUDAD
E21: VILLAVICENCIO
E22: NOMBRE Y CARGO DEL SOLICITANTE
E23: KAREN GINETH GUTIEREZ
E24: TELEFONO
E25: 3104606430
E26: CORREO ELECTRONICO
E27: QuimicoFCO@clinicaprimavera.com
B29: TIPO DE SOLICITUD
E31: QUEJA
E32: Sugerencia, Pregunta, Queja, Reclamo , Felicitación
B34: PROCESO RELACIONADO
F35: ,
B36: Tecnica | C36: x | E36: ENTREGA FUERA DEL ACUERDO DE SERVICIO | J36: ONCOLOGÍA
B38: Servicio | F38: TIPIFICACION | J38: Línea
H39: (NPT, Estériles, Oncología, No Esteriles, Magistral)
B40: DESCRIPCIÓN DE LA SOLICITUD
B41: Describa la situación citando hechos y datos ( Lote, Fecha, ID), teniendo en cuenta las siguientes preguntas: Qué? Quién? Dónde? Cuándo?
B42: Buen día, quisiera por medio de este correo reportar atrasos en la entrega de medicamentos de quimioterapia de los pacientes agendados para el día 08/04/2026, los cuales fueron citados 8 am y confirmados de manera oportuna, sin embargo siendo las 11+15 am no han sido entregada la OP, lo cual genera atrasos en los tratamientos de los pacientes, adicionalmente todos han manifestado inconformidad por lo sucedido.
G45: FECHA | H45: RESPONSABLE | J45: OBSERVACIONES
B46: Acuse de recibo de la queja al reclamante | G46: =E6 -> 46122
B47: Evaluación e investigación de la queja
B48: Solución de la queja
B49: Información al reclamante
B50: Verificación de las acciones
B51: La respuesta fue satisfactoria si no
B52: Cierre de la queja
B211: REMED MEDICAL SERVICE

Sheet ANALISIS
J1: Pagina 1 de 1
A2: ANÁLISIS E INVESTIGACIÓN DE PQRS | J2: CÓDIGO: AC-FR-055-04
A4: DATOS DE RECEPCIÓN DE PQRS
B6: Fecha PQRS: | D6: ='ATENCION '!E6 -> 46122 | F6: Regional: | G6: ='ATENCION '!G6:I6 -> LLANOS | I6: Solicitud N°: | J6: ='ATENCION '!L6 -> 130
D7: (dd/mm/aa)
A9: DESCRIPCIÓN DE LA SOLICITUD
A10: Describa la situación citando hechos y datos ( Lote, Fecha, ID), teniendo en cuenta las siguientes preguntas: Qué? Quién? Dónde? Cuándo?
A11: ='ATENCION '!B42 -> Buen día, quisiera por medio de este correo reportar atrasos en la entrega de medicamentos de quimioterapia de los pacientes agendados para el día 08/04/2026, los cuales fueron citados 8 am y confirmados de manera oportuna, sin embargo siendo las 11+15 am no han sido entregada la OP, lo cual genera atrasos en los tratamientos de los pacientes, adicionalmente todos han manifestado inconformidad por lo sucedido.
A17: INVESTIGACION
B19: Cliente / Institución
B20: ='ATENCION '!E17 -> CLINICA PRIMAVERA LLANOS
B21: Área o Proceso Involucrado en la investigación de la PQRS
B22: PRODUCCIÓN Y DIRECCIÓN TÉCNICA
B23: Responsable de la Investigación
B24: TATIANA RICO
B25: Cargo
B26: =VLOOKUP(B24,'RESPONSABLE '!A2:B40,2,0) -> DIRECTOR DE TECNICO REGIONA LLANOS
A28: CLASIFICACIÓN DE LA QUEJA
B30: MAYOR
E32: TÉCNICA : | F32: Critico, Mayor , Menor
C33: X | E33: POR SERVICIO: | F33: Imprescindible, Importante, Normal
A35: Causa del problema | F35: Que acción se va a realizar | H35: Quién será el responsable | J35: Fecha de Implementación
A42: OBSERVACIONES
B45: FECHA ENTREGA FORMATO | G45: VoBo Calidad

Sheet LISTADO MAESTRO
U1: Pagina 1 de 2
A2: LISTADO MAESTRO DE PQRS (BASE DIGITAL NACIONAL) | U2: CÓDIGO: AC-FR-056-04
A3: DATOS ENTREGADOS POR EL SOLICITANTE | J3: CLASIFICACIÓN INTERNA | O3: SEGUIMIENTO | U3: DATOS DEL CLIENTE
A4: ITEM | B4: CODIGO | C4: FECHA DE RECEPCIÓN | D4: MES | E4: REGIONAL | F4: CLIENTE | G4: INSTITUCION | H4: LÍNEA | I4: DESCRIPCIÓN | J4: TIPIFICACIÓN | K4: PROCEDE | L4: CLASIFICACIÓN | M4: PROCESO | N4: RESPONSABLE | O4: FECHA ENTREGA LÍDER | P4: FECHA RESPUESTA FINAL | Q4: ESTATUS 1 RESPUESTA | R4: FECHA VERIFICACIÓN ACCIONES | S4: ESTATUS 2 ACCIONES | T4: SOLICITUD RECIBIDA POR | U4: NOMBRE CONTACTO | V4: TELÉFONO | W4: CORREO ELECTRÓNICO E IMÁGENES | X4: ADJUNTOS | Y4: INVESTIGADAS
A5: 1 | B5: 001 | C5: 46031 | D5: ENERO | E5: CUNDINAMARCA | F5: SOCIEDAD DE CIRUGIA DE BOGOTA HOSPITAL DE SAN JOSE | G5: HOSPITAL INFANTIL UNIVERSITARIO SAN JOSE | H5: DOSIS ANTICIPADA | I5: Buenos dias. Con el presente documento quiero notificar que para el día 06/01/2026 no se ha recibido NINGUNA UNIDAD de Hidromorfona JP de la orden de producción enviada desde el martes 30/12/2025 y confirmada por ustedes el mismo día, según comunicación de ustedes se recibiría la orden el día 03/01/2026 no se brindo información oportuna sobre el retraso ni se respondió a las inquietudes expresadas, la inoportunidad de entrega genera dificultades para el cubrimiento de las necesidades de la IPS aumento el riesgo de acontecimiento de sucesos de seguridad, Esta situación también genera dificultades para la generación de la orden de producción de la semana del producto mencionado al cruzarse los requerimientos, teniendo en cuenta esto la orden será enviada el día 08/01/2026 con solicitud de llegada máximo el SÁBADO 10/01/2026 Dado lo anterior, se le solicita atentamente a Unidossis que se cumpla con los tiempos estipulados para no generar traumatismos en la operación de la IPS. | J5: ENTREGA FUERA DEL ACUERDO DE SERVICIO | K5: SI | L5: MAYOR | M5: PRODUCCIÓN Y DIRECCIÓN TÉCNICA | N5: MARTIN DURANGO | Q5: ABIERTA | S5: ABIERTA | T5: SERVICIO AL CLIENTE | U5: María Saavedra, Químico Farmacéutico | V5: 3538000 Ext. 468-422 | W5: rordenespro20211123@gmail.com | X5: ADJUNTOS | Y5: NO
A6: 1 | B6: 2 | C6: 46031 | D6: ENERO | E6: CUNDINAMARCA | F6: CHRISTUS SINERGIA | G6: CHRISTUS SINERGIA | H6: NPT | I6: Buen día. Espero se encuentren muy bien. Nos permitimos informar que el 05 de enero de 2026 se ingresaron durante la mañana las solicitudes de stocks, ajustes individualizados por pacientes y TPN. Posteriormente, en horas de la tarde, se nos comunicó que dichas solicitudes no habían sido consideradas debido a un atraso en la planta de producción. Esta situación obligó a que las modificaciones y preparaciones de dosis fueran realizadas directamente en las unidades de enfermería, alterando el flujo habitual de trabajo y generando un impacto en la organización del servicio farmacéutico. Adjunto a este correo el formato de PQR’s en el que se detalla la situación mencionada previamente. Agradecemos de antemano la atención prestada y solicitamos amablemente que se establezca un plan de acción que permita corregir y prevenir este tipo de inconvenientes en el futuro, garantizando así la eficiencia del trabajo conjunto. Quedo atenta a su respuesta. Muchas gracias. | J6: INCUMPLIMIENTO ACTIVIDADES O COMPROMISOS | K6: SI | L6: MAYOR | M6: PRODUCCIÓN Y DIRECCIÓN TÉCNICA | N6: MARTIN DURANGO | Q6: ABIERTA | S6: ABIERTA | T6: SERVICIO AL CLIENTE | U6: María Saavedra, Químico Farmacéutico | V6: N/R | W6: quimicofarmaceutico2.cpr@christus.co | X6: ADJUNTOS | Y6: NO
A7: 1 | B7: 3 | C7: 46031 | D7: ENERO | E7: CUNDINAMARCA | F7: HOSPITAL UNIVERSITARIO SAN IGNACIO | G7: HOSPITAL UNIVERSITARIO SAN IGNACIO | H7: ESTERILES | I7: Cordial saludo Unidossis, Se verifican los movimientos y se identifican las siguientes observaciones: Las unidades sobrantes de Heparinas (54 Nabuco y 52 en HUSI) corresponden a aprovechamientos tal como se verifico telefónicamente y por correo electrónico, por ende, se realizan los respectivos aprovechamientos internamente. Se identifican las siguientes novedades respecto a los movimientos de Bicarbonato: Solicitud Material Producción Fecha movimiento Código producto Descripción producto salida 25/12/2025 4057014 BICARBONATO DE SODIO 8,4% 10mEq/10ml SOL. INY. AMP IV 04057014 12 26/12/2025 4057014 BICARBONATO DE SODIO 8,4% 10mEq/10ml SOL. INY. AMP IV 04057014 1 Para el día (25/12/2025) se debían gastar (12) viales correspondientes a la preparación de 60 DUs de Bicarbonato de sodio (Se adjunta OP), sin embargo, el día (26/12/2025) se identifica la salida de (1) unidad, la cual no corresponde con ninguna preparación. Por favor solicitamos amablemente indicar a que corresponde esta unidad faltante de Bicarbonato de sodio, y si aplica, la respectiva nota crédito. Quedo atento a cualquier inquietud. Cordialmente, | J7: DIFERENCIA EN INVENTARIO EN CUSTODIA | K7: SI | L7: MAYOR | M7: PRODUCCIÓN Y DIRECCIÓN TÉCNICA | N7: MARTIN DURANGO | Q7: ABIERTA | S7: ABIERTA | T7: SERVICIO AL CLIENTE | U7: Yuri Alberto Echeverri Pineda Químico Farmacéutico Asistencial | V7: Teléfono: (601) 5946161 Ext. 3007 | W7: cytinoco@husiorgco.onmicrosoft.com | X7: ADJUNTOS | Y7: NO
A8: 1 | B8: 4 | C8: 46031 | D8: ENERO | E8: CUNDINAMARCA | F8: HOSPITAL UNIVERSITARIO CLINICA SAN RAFAEL | G8: HOSPITAL U SAN RAFAEL BOGOTA | H8: SOLIDOS | I8: Cordial saludo. Lo siguiente es para informar, que en el pedido enviado se recibió una producción de Solidos con la descripción de la razón social equivocada, por lo cual se solicita a ustedes verificar la información suministrada y hacer las correcciones pertinentes en futuras envíos de productos. Adjunto los datos correctos: Nombre: Clínica San Rafael alta complejidad Nit: 91089614-3 Direccion: calle 12 #27-100 Vía Clemente Salazar - Sabanalarga Atlántico | J8: ERROR EN ETIQUETA/CODIFICADO | K8: SI | L8: MAYOR | M8: PRODUCCIÓN Y DIRECCIÓN TÉCNICA | N8: DORIA NARVÁEZ REYES ENRIQUE | Q8: ABIERTA | S8: ABIERTA | T8: SERVICIO AL CLIENTE | U8: DIANA PADILLA BARRAZA | V8: Cel. 3105252900 Tel. (095)8784012 | W8: serviciofarmaceutico@csr.com.co | X8: ADJUNTOS | Y8: NO
A9: 1 | B9: 5 | C9: 46031 | D9: ENERO | E9: CUNDINAMARCA | F9: VIDAMEDICAL BOGOTA IPS SAS | G9: VIDAMEICA IPS | H9: ONCOLOGÍA | I9: Buenos días. Por medio del presente informo que el día 26/12/2025 se solicitó la preparación para la paciente MARIA MARTINA MATEUS VARGAS del medicamento TOCILIZUMAB 360 mg (ACTEMRA), quien tenía administración el día 27/12/2025. Estos medicamentos se enviaron el día viernes 26/12/2025 a Unidossis. El día 26/12/2025 a las 8:49pm se envía correo por parte de la jefe de sala de infusión, donde se reporta la cancelación de la paciente en mención. El día de ayer 07/01/2026 se envía orden de preparación donde se relaciona la paciente SANDRA PATRICIA CASTRO TRUJILLO y entendiendo que se tenían los viales del medicamento de la paciente cancelada el 26/12/2025, no se enviaron los viales del medicamento. El día de ayer informa Unidossis que no cuentan con los medicamentos en custodia, ya que, a pesar de la notificación de la cancelación, el medicamento fue preparado, sin embargo, no se recibió ninguna notificación al respecto, tampoco el medicamento fue enviado en físico; teniendo en cuenta que ya pasaron varios días desde el suceso. La estabilidad del medicamento diluido es de 24 horas entre 2-8°C. Esperamos una pronta respuesta sobre este caso y el respectivo plan de mejora, teniendo en cuenta que el día de hoy tuvimos que cancelar a la paciente que estaba programada, lo cual afecta la prestación de nuestros servicios en salud. | J9: DIFERENCIA EN INVENTARIO EN CUSTODIA | K9: SI | L9: MAYOR | M9: PRODUCCIÓN Y DIRECCIÓN TÉCNICA | N9: HENRY GUEVARA BOHORQUEZ | Q9: ABIERTA | S9: ABIERTA | T9: SERVICIO AL CLIENTE | U9: JUAN EDUARDO BOULLY | V9: 5144646 | W9: quimico1.scar@vidamedicalips.com.co | X9: ADJUNTOS | Y9: NO
A10: 1 | B10: 6 | C10: 46031 | D10: ENERO | E10: OCCIDENTE | F10: Clínica San Rafael de Popayán | G10: Clínica San Rafael de Popayán | H10: ONCOLOGÍA | I10: Cordial saludo Por medio del presente realizo reporte defecto de calidad sobre la preparación de la paciente Maritza Baicue Acido zoledronico 4mg, el cual se solicito en dilución de 100mL SSN 0,9%, sin embargo al verificar la preparación recepcionada se evidencia Acido Zoledrónico 4mg en 500mL SSN 0,9%. Realizo reporte con el fin de que se realice la debida verificación del caso, ya que a pesar de que en esta ocasión no afecta la administración del medicamento, puede que este error ocurra en casos futuros donde el volumen de dilución de la preparación de quimioterapia si requiera con exactitud el volumen solicitado. | J10: PRODUCTO NO CONFORME | K10: SI | L10: MAYOR | M10: PRODUCCIÓN Y DIRECCIÓN TÉCNICA | N10: KATY KARINA ORTEGA ACEVEDO | Q10: ABIERTA | S10: ABIERTA | T10: SERVICIO AL CLIENTE | U10: MARIA DEL MAR PERAFAN | V10: 8353810 | W10: quimicofarmaceutico.csrp@stewardcolombia.org | X10: ADJUNTOS | Y10: NO
A11: 1 | B11: 7 | C11: 46031 | D11: ENERO | E11: OCCIDENTE | F11: FUNDACION HOSPITAL SAN CARLOS | G11: FUNDACION HOSPITAL SAN CARLOS BOGOTA | H11: SOLIDOS | I11: Buenas tardes, cordial saludo Envió novedad presentada con la no entrega oportuna del medicamento Itraconazol tableta x 100 mg para el mes de diciembre del 2025, lo que genero que familiar de paciente interpusiera ante la EPS sanitas una queja . | J11: ENTREGA FUERA DEL ACUERDO DE SERVICIO | K11: SI | L11: MAYOR | M11: PRODUCCIÓN Y DIRECCIÓN TÉCNICA | N11: DORIA NARVÁEZ REYES ENRIQUE | P11: 45736 | Q11: CERRADA | S11: ABIERTA | T11: SERVICIO AL CLIENTE | U11: Jimmy Alejandro Calderon Rodriguez QF - farmacovigilancia | V11: 3115059392 | W11: Farmacovigilancia@fhsc.org.co | X11: ADJUNTOS | Y11: NO
A12: 1 | B12: 8 | C12: 46031 | D12: ENERO | E12: MARLY CUNDINAMARCA | F12: CLÍNICA DE MARLY JORGE CAVELIER GAVIRIA | G12: CLINICA DE MARLY CHIA | H12: SOLIDOS | I12: Buen día, Cordial saludo, mediante la presente comunico la novedad presentada el jueves 8 de enero en relación a la orden de producción enviada: Se solicitaron 12 dosis de metilprednisolona 40 mg y en la recepción técnica entregan 2 dosis con etiqueta errónea, la etiqueta tenía lidocaína como medicamento. Muchas gracias, quedo atenta a sus comentarios Cordialmente, | J12: ENTREGA FUERA DEL ACUERDO DE SERVICIO | K12: SI | L12: MAYOR | M12: PRODUCCIÓN Y DIRECCIÓN TÉCNICA | N12: DORIA NARVÁEZ REYES ENRIQUE | Q12: ABIERTA | S12: ABIERTA | T12: SERVICIO AL CLIENTE | U12: VALENTINA MARTÍNEZ MOTTA Química Farmacéutica | V12: 57 1 6532000 Ext. 7331 | W12: quimicoadj.farmacia@marlyjcg.com.co | X12: ADJUNTOS | Y12: NO
A13: 1 | B13: 9 | C13: 46027 | D13: ENERO | E13: CUNDINAMARCA SOLIDOS | F13: FARMART | G13: FARMART | H13: SOLIDOS | I13: Buen día, Se informa que se encontró una novedad durante la recepción técnica del siguiente documento. Se evidenció que el medicamento ALOPURINOL 300MG TABLETA (UNIDOSIS) | ASPEN| ZYLOPRIM presentó un mal etiquetado, ya que el producto llegó con una concentración de 30 mg, lo cual no corresponde a lo solicitado. NOTA: se solicita amablemente urgente la corrección. | J13: ERROR EN ETIQUETA/CODIFICADO | K13: SI | L13: MAYOR | M13: PRODUCCIÓN Y DIRECCIÓN TÉCNICA | N13: DORIA NARVÁEZ REYES ENRIQUE | Q13: ABIERTA | S13: ABIERTA | T13: SERVICIO AL CLIENTE | U13: ANDREA CHANTRE | V13: 3168785821 | W13: auxmedicamentoshuv@farmartips.com | X13: ADJUNTOS | Y13: NO
A14: 1 | B14: 10 | C14: 46027 | D14: ENERO | E14: CUNDINAMARCA SOLIDOS | F14: CLINICA UNIVERSIDAD DE LA SABANA | G14: CLINICA UNIVERSITARIA DE LA SABANA | H14: SOLIDOS | I14: Buenos días. Cordial saludo, El presente correo tiene como finalidad validar la razón por la cual aún no hemos recibido una orden de producción que fue enviada el pasado 23 de diciembre de 2025, teniendo en cuenta que el tiempo establecido para la adecuación de reempaque en dosis unitaria de medicamentos en forma farmacéutica sólida es de aproximadamente 8 días. A la fecha, este plazo se encuentra ampliamente superado, configurándose un incumplimiento en los tiempos acordados. Esta situación ha generado una afectación directa a los pacientes de la clínica, ya que actualmente existen pacientes activos que se encuentran en tratamiento con algunos de los medicamentos incluidos en dicha orden, los cuales han debido ser suspendidos temporalmente debido al retraso presentado. Desde el proceso de Farmacovigilancia, este escenario representa un riesgo para la continuidad terapéutica y la seguridad del paciente, por lo cual resulta prioritario contar con una pronta solución. Agradecemos nos puedan informar de manera inmediata el estado actual de la orden, la causa del incumplimiento y la fecha estimada de entrega, con el fin de tomar las acciones correspondientes y mitigar el impacto generado. No siendo más por el momento, agradezco de antemano la atención prestada y quedo atenta a sus comentarios. | J14: ERROR EN ETIQUETA/CODIFICADO | K14: SI | L14: MAYOR | M14: PRODUCCIÓN Y DIRECCIÓN TÉCNICA | N14: DORIA NARVÁEZ REYES ENRIQUE | Q14: ABIERTA | S14: ABIERTA | T14: SERVICIO AL CLIENTE | U14: SANEHIA NAHOMI MENDOZAQUINTANA | V14: 601 8617777 | W14: claudia.ramos2@clinicaunisabana.edu.co | X14: ADJUNTOS | Y14: NO
A15: 1 | B15: 11 | C15: 46038 | D15: ENERO | E15: OCCIDENTE | F15: CLINICA DESA | G15: CLINICA DESA | H15: NPT | I15: A través de este oficio notifico que, de acuerdo al contrato sostenido entre la clínica DESA S.A.S, clínica Rafel Uribe Uribe y la empresa UNIDOSSIS S.A.S, Nº 206004 relacionado con el suministro de bienes y servicios donde se realiza la elaboración de Nutriciones parenterales-NPT y la preparación de mezclas estériles de medicamentos, notifico que se ha evidenciado incumplimiento en la entrega de las preparaciones que se mencionan con anterioridad relacionado con los siguientes hechos: En la clínica DESA: El día 20 de Diciembre 2025, 8:26am, se realiza solicitud de varias NPT para los días 20 y 21, el día 21 se observa que las NPT llegaron a la clínica DESA después de las 8pm generando inoportunidad en la administración de las nutriciones. Remisionadas con el número 471246 y 470908. En la clínica DESA: El día 27 de Diciembre 2025, hora: 8:50am, se realiza solicitud de varias NPT para los días, 27 y 28, el día 27 y 28 se observa que las NPT llegaron a la clínica DESA después de las 6pm y 7pm generando inoportunidad en la administración de las nutriciones. Remisionadas con el número 472702 y 473006. En la clínica DESA: El día 27 de Diciembre 2025, hora: 8:39am, se realiza solicitud de la mezcla estéril del medicamento Cefazolina 1 g y no se elaboraron para el día que se realizó la solicitud, fueron despachadas un día después. Remisionadas con el número 472911 En la clínica DESA: El día 05 de Enero 2026, 9:44 am, se realiza solicitud de varias NPT para ser entregadas el mismo día, se observa que las NPT llegaron a la clínica DESA a las 6:42pm, generando inoportunidad en la administración de las nutriciones. Remisionadas con el número 474882 En la clínica Nueva Rafael Uribe: El día 05 de Enero 20 realiza solicitud de las mezclas estériles de los medicamentos Cefazolina 2g, Piperacilina y Tazobactam 4.5g, Ampicilina y Sulbactam 3 g, Piperacilina y Tazobactam 13.5g y no fueron preparadas. Desde la dirección técnica del servicio farmacéutico de la clínica DESA y como interventor es muy importante hacer seguimiento al cumplimiento del contrato, luego de tener estas observaciones con respecto a las inoportunidades que se vienen presentado con la empresa UNIDOSSIS S.A.S, yo, como veedor del cumplimiento, notifico para su conocimiento, información que será trasmitida al área jurídica | J15: ENTREGA FUERA DEL ACUERDO DE SERVICIO | K15: SI | L15: MAYOR | M15: PRODUCCIÓN Y DIRECCIÓN TÉCNICA | N15: ANGELA MARCELA PARRA ESPITIA | Q15: ABIERTA | S15: ABIERTA | T15: SERVICIO AL CLIENTE | U15: Yeison Jacob Moreno Murillo Químico Farmacéutico. Director técnico | V15: Tel.: 3814161 Ext. 102 - 117 | W15: yeison.moreno@clinicadesa.com.co | X15: ADJUNTOS | Y15: NO
A16: 1 | B16: 12 | C16: 46041 | D16: ENERO | E16: CUNDINAMARCA | F16: HOSPITAL UNIVERSITARIO SAN IGNACIO | G16: HOSPITAL UNIVERSITARIO SAN IGNACIO | H16: ESTERILES | I16: Buenas tardes equipo Unidossis, reciban un cordial saludo, Confirmo el recibo de la respuesta a los retrasos presentados en el último trimestre del 2025, sin embargo, para dar cierre efectivo de las solicitudes del 2025 aún tenemos pendiente los siguientes casos: FECHA RESPONSABLE DESCRIPCION 14/10/2025 YURI ECHEVERRI DU Heparia con pivote roto (pendiente respuesta con el reporte al proeedor) 7/12/2025 ERIKA ROMERO Du piperacilina con las etiquetas cruzadas, no corresponde el volumen de la jeringa con el declarado en la etiqueta (pendiente respuesta con acciones de mejora) 15/12/2025 YURI ECHEVERRI OP de 50 DU de succinilcolina, llegan 49 (pendiente respuesta con acciones de mejora y emisión de nota crédito por la unidad faltante) 26/12/2025 YURI ECHEVERRI OP de 50 DU de succinilcolina, programada para entrega el 24/12/2025, llega el 25/12/2025 y solo llegan 49 unidades (pendiente respuesta con acciones de mejora y emisión de nota crédito por la unidad faltante) Solicitamos amablemente la colaboración con la revisión de los fallos de calidad. | J16: ENTREGA FUERA DEL ACUERDO DE SERVICIO | K16: SI | L16: MAYOR | M16: PRODUCCIÓN Y DIRECCIÓN TÉCNICA | N16: MARTIN DURANGO | P16: YA SE ENTREGARON TODAS LAS RESPUESTAS DE 2025 | Q16: CERRADA | S16: ABIERTA | T16: SERVICIO AL CLIENTE | U16: Claudia Tinoco Rairán Química Farmacéutica de Aseguramiento de la Calidad | V16: Teléfono: 57 (1) 5946161 Ext. 1066 | W16: cytinoco@husi.org.co | X16: ADJUNTOS | Y16: NO
A17: 1 | B17: 13 | C17: 46041 | D17: ENERO | E17: OCCIDENTE | F17: EMSSANAR EPS | G17: EMSSANAR EPS | H17: ADMINISTRATIVO | I17: Cordial saludo Se reitera la solicitud, teniendo en cuenta que a la fecha no ha sido posible legalizar los recursos girados bajo modalidad de anticipo que a la fecha ascienden a $4.886.100. Por otra parte, se ha intentado establecer una comunicación telefónica con el propósito de conocer el estado de los recursos a las siguientes líneas telefónicas 601-244-40-02 y 3168788032 sin éxito. Cliente Razón social Nro. docto. cruce Fecha docto cruce Total COP Notas 900281394 UNIDOSSIS S.A.S AN-00055676 30/09/2025 4.886.100,00 ANTC. 55676 PTE. LUCIA CASTRO RC. 1108341703 INFUSION DE ALIMENTACION PARENTERAL - OR En caso de presentarse alguna novedad relacionada con la radicación, se solicita informar por este medio con el fin de programar una mesa de trabajo que permita brindar acompañamiento y capacitación por parte del equipo de radicación, en el proceso de cargue de facturas y soportes a través de la plataforma RISPLINK. En caso de que el servicio no haya sido prestado, se solicita el reintegro de los recursos correspondientes, los cuales deberán ser consignados en la cuenta bancaria adjunta. Agradezco la atención prestada | J17: INCUMPLIMIENTO ACTIVIDADES O COMPROMISOS | K17: SI | L17: MAYOR | M17: PRODUCCIÓN Y DIRECCIÓN TÉCNICA | N17: MANUEL GASCA | O17: 46053 | P17: 46053 | Q17: CERRADA | R17: 31/*01/2026 | S17: CERRADA | T17: SERVICIO AL CLIENTE | U17: STEPHANNY CALPA Legalización Anticipos Salud | V17: 3176990583 | W17: legalizacionanticipossalud@emssanareps.co | X17: ADJUNTOS | Y17: NO
A18: 1 | B18: 14 | C18: 46041 | D18: ENERO | E18: CUNDINAMARCA | F18: SOCIEDAD DE CIRUGIA DE BOGOTA HOSPITAL DE SAN JOSE | G18: HOSPITAL INFANTIL UNIVERSITARIO SAN JOSE | H18: NPT | I18: Asunto: Queja terminación NPT Buenos días. Se adjunta documento de queja con relación al asunto. Sin otro particular, gracias por la atención. Cordial saludo, Juana Vargas Químico Farmacéutico Servicio Farmacéutico Sociedad de Cirugía de Bogotá Hospital de San José 3538000 Ext. 468-422 | J18: PRODUCTO NO CONFORME | K18: SI | L18: MAYOR | M18: PRODUCCIÓN Y DIRECCIÓN TÉCNICA | N18: MARTIN DURANGO | Q18: ABIERTA | S18: ABIERTA | T18: SERVICIO AL CLIENTE | U18: Juana Vargas Químico Farmacéutico | V18: 3538000 Ext. 468-422 | W18: rordenespro20211123@gmail.com | X18: ADJUNTOS | Y18: NO
A19: 1 | B19: 15 | C19: 46041 | D19: ENERO | E19: CUNDINAMARCA | F19: CHRISTUS SINERGIA | G19: CHRISTUS SINERGIA | H19: TODAS | I19: Buen día, Espero se encuentren muy bien. Por medio del presente, me permito radicar una PQR debido al retraso en la entrega de las adecuaciones y ajustes de medicamentos estériles y nutriciones parenterales solicitadas en horas de la mañana del día de hoy. Adjunto a este correo la PQR correspondiente, así como un fragmento del contrato en el cual se establecen los horarios de entrega. De acuerdo con lo allí estipulado, se evidencia un incumplimiento en la prestación del servicio en la fecha mencionada. Agradecemos su pronta respuesta y las acciones que consideren pertinentes, con el fin de fortalecer los procesos y garantizar el bienestar y la seguridad de los pacientes. Muchas gracias. | J19: ENTREGA FUERA DEL ACUERDO DE SERVICIO | K19: SI | L19: MAYOR | M19: PRODUCCIÓN Y DIRECCIÓN TÉCNICA | N19: ANGELA MARCELA PARRA ESPITIA | Q19: ABIERTA | S19: ABIERTA | T19: SERVICIO AL CLIENTE | U19: YESICA ALEJANDRA GOEZ | V19: N/R | W19: quimicofarmaceutico2.cpr@christus.co | X19: ADJUNTOS | Y19: NO
A20: 1 | B20: 16 | C20: 46042 | D20: ENERO | E20: SANTANDER | F20: SIES SALUD | G20: SIES SALUD | H20: ONCOLOGÍA | I20: Buenos días, Señores Unidosis: Por medio de la presente queremos informar el error identificado en las cédulas de todos los pacientes con preparaciones de oncología correspondientes al día 05 de enero de 2026. Si bien el incidente no generó consecuencias graves, sí representó un riesgo potencial para la seguridad de los pacientes, motivo por el cual consideramos importante revisarlo con ustedes. Con el fin de fortalecer los procesos y garantizar la confiabilidad de la información, solicitamos nos compartan: Las acciones de mejora que se implementarán para evitar que este tipo de situaciones se repitan. Los ajustes o controles adicionales que consideren pertinentes para reforzar la seguridad en la preparación y validación de datos de los pacientes. Agradecemos su atención y el compromiso con la mejora continua, así como la disposición para trabajar conjuntamente en la prevención de futuros inconvenientes. Atentamente, | J20: PRODUCTO NO CONFORME | K20: SI | L20: MAYOR | M20: PRODUCCIÓN Y DIRECCIÓN TÉCNICA | N20: IVAN PEREIRA | O20: 46048 | P20: 46048 | Q20: CERRADA | S20: ABIERTA | T20: SERVICIO AL CLIENTE | U20: David José Ortega Redondo Profesional Asistencial Químico Farmacéutico | V20: (7) 6970001 - 319 2729798 | W20: dortegar@siessalud.com.co | X20: ADJUNTOS | Y20: NO
A21: 1 | B21: 17 | C21: 46042 | D21: ENERO | E21: SANTANDER | F21: CLINICA MATERNO INFANTIL DE SAN LUIS | G21: CLINICA SAN LUIS | H21: ONCOLOGÍA | I21: Se recibe el día 22 de diciembre en turno de la noche cafeína en unidosis solicitada 20 mg. Llega medicamento con etiqueta marcada de 20 mg, pero se observa solo 0.1 CC. la dosis corresponde a 1 CC. # LOTE 07213R53786 Revisando la orden de produccion enviada a unidosis el día 22 de diciembre a las 15;57:34, la dosis es de 20 MG de cafeina a nombre de NICOLAS CAMPO LOZANO con registro 3053764 Favor enviar respuesta de lo acontecido Cordial saludo | J21: ERROR EN ETIQUETA/CODIFICADO | K21: SI | L21: MAYOR | M21: PRODUCCIÓN Y DIRECCIÓN TÉCNICA | N21: IVAN PEREIRA | O21: 46048 | P21: 206/21/2026 | Q21: CERRADA | S21: ABIERTA | T21: SERVICIO AL CLIENTE | U21: N/R | V21: N/R | W21: quimico.farmaceutico@clinicasanluis.com.co> | X21: ADJUNTOS | Y21: NO
A22: 1 | B22: 18 | C22: 46043 | D22: ENERO | E22: COSTA | F22: CLINICA INTERNACIONAL LA MISERICORDIA. OINSAMED | G22: CLINICA INTERNACIONAL LA MISERICORDIA OINSAMED | H22: ESTERILES | I22: Buenas tardes La presente es para informar que en el dia de hoy llegaron de parte de ustedes 3 unidosis de Piperacilina+tazobactam de 4,5 g sin el empaque externo correspondiente al paciente Jose Gomez Altamar, debido a que no cumplió con la recepción técnica se devuelve las preparaciones. Adjunto foto | J22: ERROR DE EMPAQUE | K22: SI | L22: MAYOR | M22: PRODUCCIÓN Y DIRECCIÓN TÉCNICA | N22: ESTEFANIA MARTINEZ MARTINEZ | O22: 46043 | P22: 46043 | Q22: CERRADA | S22: ABIERTA | T22: SERVICIO AL CLIENTE | U22: JANELLY OTERO MEDRANO Químico farmacéutico | V22: 3112640 ext 1010 | W22: produccioncm@lmci.com.co | X22: ADJUNTOS | Y22: NO
A23: 1 | B23: 19 | C23: 46044 | D23: ENERO | E23: CUNDINAMARCA SOLIDOS | F23: HOSPITAL UNIVERSITARIO SAN IGNACIO | G23: HOSPITAL UNIVERSITARIO SAN IGNACIO | H23: SOLIDOS | I23: Buenas tardes Francisco, te remito las fotos de la novedad de reempaque detectada el día de hoy. Cordialmente, | J23: ERROR DE RE EMPAQUE | K23: SI | L23: MAYOR | M23: PRODUCCIÓN Y DIRECCIÓN TÉCNICA | N23: DORIA NARVÁEZ REYES ENRIQUE | Q23: ABIERTA | S23: ABIERTA | T23: SERVICIO AL CLIENTE | U23: Viviana Andrea Pinzón García QF Esp.Jefe de Servicio Farmacéutico | V23: Teléfono: 57 (1) 5946161 Ext. 1045 | W23: vapinzon@husi.org.co | X23: ADJUNTOS | Y23: NO
A24: 1 | B24: 20 | C24: 46045 | D24: ENERO | E24: CUNDINAMARCA | F24: HOSPITAL UNIVERSITARIO SAN IGNACIO | G24: HOSPITAL UNIVERSITARIO SAN IGNACIO | H24: ESTERILES | I24: Cordial saludo Unidossis, El presente correo es para reportar las siguientes novedades/inconvenientes respecto a la entrega de la OP de Heparinas. Las DUs de Heparina debían llegar para el día (20/01/2026), sin embargo, llegaron hasta el día (22/01/2026) en horas de la tarde. Esto conlleva a la entrega NO oportuna de los medicamentos a los pacientes. Dicho lo anterior se solicita: Acciones de mejora a implementar para minimizar este tipo de inconvenientes. Reunión con el fin de esclarecer nuevamente los acuerdos de servicio, para que resulten favorables para ambas partes. Quedo atento a cualquier inquietud. Cordialmente, | J24: ENTREGA FUERA DEL ACUERDO DE SERVICIO | K24: SI | L24: MAYOR | M24: PRODUCCIÓN Y DIRECCIÓN TÉCNICA | N24: MARTIN DURANGO | O24: 46094 | P24: 46094 | Q24: CERRADA | S24: ABIERTA | T24: SERVICIO AL CLIENTE | U24: Yuri Alberto Echeverri Pineda Químico Farmacéutico Asistencial | V24: Teléfono: (601) 5946161 Ext. 3007 | W24: yaecheverri@husi.org.co | X24: ADJUNTOS | Y24: NO
A25: 1 | B25: 21 | C25: 46048 | D25: ENERO | E25: OCCIDENTE | F25: FUND CLINICA INFANTIL CLUB NOEL | G25: FUND CLINICA INFANTIL CLUB NOEL | H25: ONCOLOGÍA | I25: Por medio del presente me permito reportar una inconformidad relacionada con la llegada de las quimioterapias y PME del sábado 24 de enero de 2026. Los medicamentos llegaron a la clínica a las 6:20 p.m. para su entrega. Cabe resaltar que el correo con la orden de producción de las quimioterapias se envió a Unidossis a las 8:06 a.m. No obstante, las preparaciones llegaron a las 6:20 p.m., a pesar de que inicialmente la química Samantha había informado que estarían llegan a la clínica a las 2:00 p.m. A las 3:00 p.m., la química Samantha se comunicó con la regente Karen Carabalí para preguntar si era posible realizar la entrega a las 5:00 p.m., a lo cual se le indicó que no, dado que los pacientes ya debían estar recibiendo su tratamiento. Posteriormente, a las 5:00 p.m. Se realizó otra llamada, en la cual la química Samantha informó que las preparaciones estaban próximas a llegar. Sin embargo, estas solo fueron entregadas a las 6:20 p.m. Adicionalmente, se presentó un error en la preparación para el paciente Janer Arley Gómez Flores, a quien se le envió preparar citarabina 500 mg (cantidad 2) en dosis de 225 mg en un volumen de 100 ml. Sin embargo, al momento de la entrega en la clínica se recibió únicamente 1 preparación, razón por la cual el domingo se envió a preparar el faltante para que el paciente pudiera completar su tratamiento. adjunto imagen de la orden de preparación del dia sabado 24/01 /2026 donde se evidencia que se envió a preparar cantidad 2 citarabina 500mg Este retraso ocasionó afectaciones en el tratamiento de 8 pacientes con tratamiento de quimioterapia, así como en los pacientes de las PME, considerando que algunos tenían dosis programadas a las 6:00 p.m. | J25: ENTREGA FUERA DEL ACUERDO DE SERVICIO | K25: SI | L25: MAYOR | M25: PRODUCCIÓN Y DIRECCIÓN TÉCNICA | N25: ANGELA MARCELA PARRA ESPITIA | Q25: ABIERTA | S25: ABIERTA | T25: SERVICIO AL CLIENTE | U25: Karen Carabali Abonia Regente de Farmacia | V25: Tel: 602 485 44 04 Ext.: 1128 | W25: central.mezclas@fciclubnoel.com | X25: ADJUNTOS | Y25: NO
A26: 1 | B26: 22 | C26: 46048 | D26: ENERO | E26: CUNDINAMARCA | F26: HOSPITAL UNIVERSITARIO SAN IGNACIO | G26: HOSPITAL UNIVERSITARIO SAN IGNACIO | H26: ESTERILES | I26: Cordial saludo El presente con el fin de reportar queja en cuanto al retraso en entrega de las dosis unitarias de estériles del día 23 de enero las cuales se recibieron a las 18:39 (horario pactado 17:00). Agradezco la atención prestada y quedo atenta a comentarios. | J26: ENTREGA FUERA DEL ACUERDO DE SERVICIO | K26: SI | L26: MAYOR | M26: PRODUCCIÓN Y DIRECCIÓN TÉCNICA | N26: MARTIN DURANGO | O26: 46094 | P26: 46094 | Q26: CERRADA | S26: ABIERTA | T26: SERVICIO AL CLIENTE | U26: Luisa Ovalle Químico Farmacéutico Asistencial | V26: Teléfono: (601) 5946161 Ext. 3007 | W26: luovalle@husi.org.co | X26: ADJUNTOS | Y26: NO
A27: 1 | B27: 23 | C27: 46049 | D27: ENERO | E27: CUNDINAMARCA | F27: CLINICA UNIVERSIDAD DE LA SABANA | G27: CLINICA UNIVERSITARIA DE LA SABANA | H27: DOSIS ANTICIPADA | I27: Buen día, Mediante el presente reporto, el día sábado recibimos la orden de producción 479522 correspondiente a 100 JP de hidromorfona lote: RC2664494, y al realizar la inspección de calidad, se evidencia una jeringa con particulas en la parte superior y color oxido. Solicitamos una revisión de lo ocurrido. Asimismo, agradecemos nos informen las medidas correctivas que se implementarán para evitar que estos errores se repitan. Además, requerimos que se nos indique cómo se realizará la reposición de la unidad afectada. | J27: PRODUCTO NO CONFORME | K27: SI | L27: MAYOR | M27: PRODUCCIÓN Y DIRECCIÓN TÉCNICA | N27: MARTIN DURANGO | Q27: ABIERTA | S27: ABIERTA | T27: SERVICIO AL CLIENTE | U27: MARIA ALEJANDRA CAMPOS ACOSTA | V27: 8617777 | W27: maria.campos2@clinicaunisabana.edu.co | X27: ADJUNTOS | Y27: NO
A28: 1 | B28: 24 | C28: 46049 | D28: ENERO | E28: CUNDINAMARCA | F28: CLINICA ZENTRIA LA MILAGROSA SAS | G28: CLINICA ZENTRIA LA MILAGROSA SAS | H28: ONCOLOGÍA | I28: Buen día, cordial saludo. El día de ayer se mandó la solicitud de preparación de medicamento Oncológico, a las 2:59pm (adjunto evidencia). A las 9 de la mañana de hoy se recibe la llamada de que no fue preparado porque el correo fue recibido muy tarde; a pesar de que expresaron que se podía mandar el día de hoy lo antes posible, no se puede recibir en horas de la tarde debido a que la programación de los pacientes y la enfermera jefe ya se encontraba establecida. Ante estas eventualidades agradezco se genere un plan de acción. Recomendamos contestar el recibido de los correos, así mismo notificar si no se va a poder preparar sea porque se mandó tarde o porque se recibió tarde, esto para poder coordinar con el servicio de Quimioterapia y con los pacientes. Quedo atenta, gracias. | J28: ENTREGA FUERA DEL ACUERDO DE SERVICIO | K28: SI | L28: MAYOR | M28: PRODUCCIÓN Y DIRECCIÓN TÉCNICA | N28: MARTINEZ GRANADOS MARIA VICTORIA | Q28: ABIERTA | S28: ABIERTA | T28: SERVICIO AL CLIENTE | U28: ANDREA ARDILA PINEDA | V28: 4351847 | W28: andrea.ardila@zentria.com.co | X28: ADJUNTOS | Y28: NO
A29: 1 | B29: 25 | C29: 46049 | D29: ENERO | E29: CUNDINAMARCA | F29: SOCIEDAD DE CIRUGIA DE BOGOTA HOSPITAL DE SAN JOSE | G29: HOSPITAL DE SAN JOSE | H29: NPT | I29: "Buen día, Por medio de la presente es para informar que el día 26/01/2026 se recibió una nutrición sin el peso correspondiente de la paciente H/HAREN ESTEFANIA JIMENEZ SILVA, es importante resaltar que las nutriciones deben venir con el peso ya que es nuestra forma de darle seguimiento y validar que se encuentre en los rangos de aceptación. Se realizó la verificación de los volumenes de la nutrición y correspondian, sin embargo, es necesario que todas las nutriciones vengan con el peso. Agradecemos su colaboración para que esta situción no se vuelva a presentar. Se adjunta evidencia fotografica. " | J29: PRODUCTO NO CONFORME | K29: SI | L29: MAYOR | M29: PRODUCCIÓN Y DIRECCIÓN TÉCNICA | N29: MARTIN DURANGO | Q29: ABIERTA | S29: ABIERTA | T29: SERVICIO AL CLIENTE | U29: Juana Camila Vargas Yasser - Química Farmacéutica | V29: 3538000 Ext. 468 | W29: rordenespro20211123@gmail.com | X29: ADJUNTOS | Y29: NO
A30: 1 | B30: 26 | C30: 46050 | D30: ENERO | E30: COSTA | F30: CLINICA MAICA NUESTRA | G30: CLINICA MAICAO NUESTRA | H30: NPT | I30: Cordial saludo, Por medio del presente, nos permitimos solicitar muy respetuosamente que cualquier inconveniente relacionado con la producción y/o transportación de las Nutriciones Parenterales Totales (NPT) sea notificado de manera inmediata, en la medida de lo posible. Lo anterior se fundamenta en que nuestra Unidad de Cuidados Intensivos Neonatal cuenta actualmente con pacientes hospitalizados a la espera de este soporte nutricional, el cual resulta crítico para su manejo clínico. Si bien comprendemos que UNIDOSSIS se encuentra ubicado en la ciudad de Barranquilla y nuestra institución en Maicao, La Guajira, y que la distancia representa un factor relevante en los tiempos de entrega, se hace indispensable contar con una comunicación oportuna que nos permita tomar medidas clínicas y administrativas preventivas. De manera puntual, informamos que actualmente contamos con tres pacientes en espera de la NPT, correspondiente a la orden de despacho No. 4456675, la cual fue recibida en nuestra institución a las 10:35 a.m. del día de hoy, situación que genera un impacto directo en la continuidad del tratamiento de los pacientes neonatales. Adicionalmente, agradecemos nos sea suministrado un medio que permita realizar la trazabilidad completa del pedido, de tal forma que podamos conocer de manera oportuna el estado del mismo (producción, despacho y transporte) y así tomar las medidas asistenciales necesarias para garantizar la seguridad del paciente y la continuidad del tratamiento. Agradecemos de antemano su colaboración y disposición para fortalecer los canales de comunicación. Quedamos atentos a cualquier información adicional. | J30: ENTREGA FUERA DEL ACUERDO DE SERVICIO | K30: SI | L30: MAYOR | M30: PRODUCCIÓN Y DIRECCIÓN TÉCNICA | N30: MARTINEZ GRANADOS MARIA VICTORIA | Q30: ABIERTA | S30: ABIERTA | T30: SERVICIO AL CLIENTE | U30: VALENTINA MENDOZA GALEANO Directora Técnica del Servicio Farmacéutico ALDAIR DE LA CRUZ PERTUZ Químico Farmacéutico Asistencial | V30: ☎️ Teléfono: (605) 7256500 Ext. 1005 | W30: farmacia@clinicamaicao.com | X30: ADJUNTOS | Y30: NO
A31: 1 | B31: 27 | C31: 46050 | D31: ENERO | E31: CUNDINAMARCA | F31: HOSPITAL UNIVERSITARIO SAN IGNACIO | G31: HOSPITAL UNIVERSITARIO SAN IGNACIO | H31: ESTERILES | I31: Cordial saludo El presente con el fin de reportar queja en cuanto al retraso en entrega de las dosis unitarias de estériles del día 27 de enero las cuales se recibieron a las 18:27 (horario pactado 17:00). Adjunto envío documento. Agradezco la atención prestada y quedo atenta a comentarios. Cordialmente | J31: ENTREGA FUERA DEL ACUERDO DE SERVICIO | K31: SI | L31: MAYOR | M31: PRODUCCIÓN Y DIRECCIÓN TÉCNICA | N31: MARTIN DURANGO | Q31: ABIERTA | S31: ABIERTA | T31: SERVICIO AL CLIENTE | U31: Luisa Ovalle Químico Farmacéutico Asistencial | V31: Teléfono: (601) 5946161 Ext. 3007 | W31: luovalle@husi.org.co | X31: ADJUNTOS | Y31: NO
A32: 1 | B32: 28 | C32: 46050 | D32: ENERO | E32: CUNDINAMARCA | F32: VANTIVE S.A.S. | G32: VANTIVE | H32: DOSIS ANTICIPADA | I32: Buen día Cordial saludo Por medio de la presente solicito la colaboración para realizar recolección y cambio en físico de 50 unidosis de HEPARINA SODICA 3000UI/5ML con la REMISION 476375 ya que se evidencia que la solicitud fue emitida y grabada por HEPARINA SODICA 5000UI . | J32: ERROR EN ETIQUETA/CODIFICADO | K32: SI | L32: MAYOR | M32: PRODUCCIÓN Y DIRECCIÓN TÉCNICA | N32: MARTIN DURANGO | Q32: ABIERTA | S32: ABIERTA | T32: SERVICIO AL CLIENTE | U32: Carlos Alberto Vergara Vergara Sr Analista de Inventarios RCS – Procurement | V32: Celular: 3154947751 | W32: Email: carlos.vergara@vantive.com | X32: ADJUNTOS | Y32: NO
A33: 1 | B33: 29 | C33: 46051 | D33: ENERO | E33: CUNDINAMARCA | F33: CLINICA UNIVERSIDAD DE LA SABANA | G33: CLINICA UNIVERSITARIA DE LA SABANA | H33: DOSIS ANTICIPADA | I33: Buen día, Mediante el presente reporto, el día de ayer miercoles 28/01/2026 recibimos la orden de producción 480543 correspondiente a 100 JP de hidromorfona lote: RC2675942, y al realizar la inspección de calidad, se evidencia una jeringa sin etiqueta interna y una sin identificación ni interna ni externa. Solicitamos una revisión de lo ocurrido. Asimismo, agradecemos nos informen las medidas correctivas que se implementarán para evitar que estos errores se repitan. Además, requerimos que se nos indique cómo se realizará la reposición de la unidad afectada. | J33: PRODUCTO NO CONFORME | K33: SI | L33: MAYOR | M33: PRODUCCIÓN Y DIRECCIÓN TÉCNICA | N33: MARTIN DURANGO | Q33: ABIERTA | S33: ABIERTA | T33: SERVICIO AL CLIENTE | U33: MARIA ALEJANDRA CAMPOS ACOSTA | V33: 8617777 | W33: maria.campos2@clinicaunisabana.edu.co | X33: ADJUNTOS | Y33: NO
A34: 1 | B34: 30 | C34: 46051 | D34: ENERO | E34: CUNDINAMARCA | F34: FUNDACION ABOOD SHAIO | G34: FUND SHAIO | H34: DOSIS ANTICIPADA | I34: Los medicamentos se enviarán esta misma tarde. Tener en cuenta que la Ketamina es un medicamento de control especial, por lo que se requiere reposición lo más pronto posible. Del mismo modo, se solicita el reempaque de la tableteria con la información legible (en el reempaque también van medicamentos controlados como Hidromorfona 2,5 mg tableta). ASUNTO: Reclamo técnico 20-26 KETAMINA 10MG/ML JERINGA PRELLENA X 5ML LOTE RC2645962 "Jeringa la cual se encuentra dentro de la bolsa sellada y al abrir la bolsa se encuentra jeringa solo con 3CC de ketamina y protector de punta de jeringa roto" ASUNTO: Reclamo técnico 21-26 JP HEPARINA 5000 UNDX 1ML "Se decide administrar heparina, se pincha el paciente y se visualiza que no hay medicamento; vale la pena resaltar que estaba sellada la bolsa de Unidossis." | J34: PRODUCTO NO CONFORME | K34: SI | L34: MAYOR | M34: PRODUCCIÓN Y DIRECCIÓN TÉCNICA | N34: MARTIN DURANGO | Q34: ABIERTA | S34: ABIERTA | T34: SERVICIO AL CLIENTE | U34: Oscar Alfonso Vargas Bautista Químico(a) Farmacéutico(a) | V34: PBX (601) 593 8210 | W34: alfonso.vargas@shaio.org | X34: ADJUNTOS | Y34: NO
A35: 1 | B35: 31 | C35: 46051 | D35: ENERO | E35: CUNDINAMARCA | F35: FUNDACION ABOOD SHAIO | G35: FUND SHAIO | H35: SOLIDOS | I35: ASUNTO: Reclamo técnico 22-26 TraZODona 50 mg CAP "No se evidencia medicamento dentro del reempaque ni información del medicamento; se saca del paquete de la bolsa de trazodona, se evidencia reempaque sellado." ASUNTO: Reclamo técnico 23-26 CALCITRIOL 0,25MCG TAB “Se evidencian 2 unidades de Calcitriol en 1 mismo reempaque" ASUNTO: Reclamo técnico 24-26 ELTROMBOPAG X 50MG TABLETA REC "Información del medicamento ilegible" ASUNTO: Reclamo técnico 34-26 HIDROMORFONA 2,5MG TAB "información no legible del reempaque" ASUNTO: Reclamo técnico 430-25 ACETAMINOFEN 500 MG TAB "Información ilegible, código de barras borrado" | J35: PRODUCTO NO CONFORME | K35: SI | L35: MAYOR | M35: PRODUCCIÓN Y DIRECCIÓN TÉCNICA | N35: MARTIN DURANGO | Q35: ABIERTA | S35: ABIERTA | T35: SERVICIO AL CLIENTE | U35: Oscar Alfonso Vargas Bautista Químico(a) Farmacéutico(a) | V35: PBX (601) 593 8210 | W35: alfonso.vargas@shaio.org | X35: ADJUNTOS | Y35: NO
A36: 1 | B36: 32 | C36: 46051 | D36: ENERO | E36: COSTA | F36: CLINICA INTERNACIONAL LA MISERICORDIA. OINSAMED | G36: CLINICA INTERNACIONAL LA MISERICORDIA OINSAMED | H36: SOLIDOS | I36: ASUNTO: MEDICAMENTO SIN EMPAQUE EXTERNO Reciba un cordial saludo. Por medio de la presente nos dirigimos a ustedes con el fin de dar respuesta a la queja interpuesta, con número de radicado 150126-1 MEDICAMENTO SIN EMPAQUE EXTERNO, no sin antes agradecerles por la realización de estos reportes ya que contribuye con nuestros procesos de mejora continua, y nos impulsa a seguir trabajando para mantener la satisfacción del cliente. | J36: PRODUCTO NO CONFORME | K36: SI | L36: MAYOR | M36: PRODUCCIÓN Y DIRECCIÓN TÉCNICA | N36: MARTIN DURANGO | Q36: ABIERTA | S36: ABIERTA | T36: SERVICIO AL CLIENTE | U36: ISIS MADALÉN MONTENEGRO QUINTERO Coordinador Logístico | V36: Fijo: 3112640 Ext: 1011 Móvil: 350-6007491 | W36: coor.farmacia@lmci.com.co | X36: ADJUNTOS | Y36: NO
A37: 1 | B37: 33 | C37: 46051 | D37: ENERO | E37: COSTA | F37: CLINICA BAHIA | G37: CLINICA BAHIA | H37: SOLIDOS | I37: Buenos días, Saludos cordiales. De acuerdo con lo conversado vía telefónica, me permito informar el producto no conforme detectado durante el proceso de recepción Tecnica de los preparados del día 28/01/2026, el cual 1 unidad presentó salida de líquido (fuga), motivo por el cual no pudo ser dispensado al servicio de UCI, lo cual nos genera un faltante en el invetario del servicio farmaceutico. Detalle del producto: Medicamento: Vancomicina Concentración / Volumen: 1 g / 250 mL Lote interno: RB2680179 Cantidad: 1 unidad Se adjunta formato institucional de medicamentos averiados y registro fotográfico de la novedad. Agradecemos tener en cuenta que, al momento de la facturación del día 28/01/2026, no incluir esta unidosis y se solicita la reposición en inventario de las 2 ampollas correspondientes a la preparación. | J37: PRODUCTO NO CONFORME | K37: SI | L37: MAYOR | M37: PRODUCCIÓN Y DIRECCIÓN TÉCNICA | N37: MARTINEZ GRANADOS MARIA VICTORIA | Q37: ABIERTA | S37: ABIERTA | T37: SERVICIO AL CLIENTE | U37: Brenda Morales Tinoco Quimico Farmaceutico. | V37: N/R | W37: controlgasesmedicinales@clinicabahia.com | X37: ADJUNTOS | Y37: NO
A38: 1 | B38: 34 | C38: 46051 | D38: ENERO | E38: CUNDINAMARCA | F38: FUNDACION HOSPITAL SAN CARLOS | G38: FUNDACION HOSPITAL SAN CARLOS BOGOTA | H38: SOLIDOS | I38: Buenas tardes, cordial saludo Me permito informar que actualmente se ha venido identificando novedades con los medicamentos que llegan reempacados a la institución fundación hospital san Carlos. Las novedades están relacionadas principalmente con el empaque, como se muestra en las imágenes adjuntas // Se están entregando medicamentos que no cuentan con la ranura de separación, generando que al momento de la dispensación se rompa todo el empaque lo cual lleva a que el medicamento quede suelto y sin ningún tipo de identificación. Medicamento sin ranura para la separación Esta novedad técnica esta generando que se realicen reprocesos [ dado que se tiene que utilizar una persona de manera diaria para que realice el respectivo corte o separación | J38: PRODUCTO NO CONFORME | K38: SI | L38: MAYOR | M38: PRODUCCIÓN Y DIRECCIÓN TÉCNICA | N38: DORIA NARVÁEZ REYES ENRIQUE | P38: 46101 | Q38: CERRADA | S38: ABIERTA | T38: SERVICIO AL CLIENTE | U38: Jimmy Alejandro Calderon Rodriguez QF - FHSC | V38: N/R | W38: farmacovigilancia@fhsc.org.co | X38: ADJUNTOS | Y38: NO
A39: 1 | B39: 35 | C39: 46051 | D39: ENERO | E39: CUNDINAMARCA | F39: FARMART | G39: FARMART | H39: SOLIDOS | I39: Buen día, Informo las novedades encontradas mientras se realizaba el proceso de recepción de unidosis: Código Interno Descripción Lote Fecha Vencimiento Stock Observacion 39598 GABAPENTIN 300MG TABLETA (UNIDOSIS) | LEGRAND | KAPTIN B02505 2027-07-30 1 averia 43507 QUETIAPINA 25MG TABLETA (UNIDOSIS) | HETERO LABS LIMITED| TIQUEPIN| TQD241102 2027-10-30 10 sobrante 44074 SILDENAFIL 50MG TABLETA (UNIDOSIS) | GENFAR | F01689E 2027-07-30 212 error en lote 50265 ACETAMINOFEN + CODEINA 325MG + 30MG TABLETA (UNIDOSIS) | NOVAMED | APRIX 2511004637 2027-11-30 16 pendiente por entrega El medicamento que se indica como sobrante se evidencio que el paquete indicaba 50 unidades pero fisicamente llegaron 60 unidades. En el caso del medicamento ACETAMINOFEN + CODEINA 325MG + 30MG TABLETA (UNIDOSIS) | NOVAMED | APRIX, se enviaron a reempaque un total de 200 unidades. No obstante, al momento de realizar el proceso de recepción de unidosis y la revisión del documento de reempaque, se evidencia que fueron remisionadas y entregadas únicamente 184 unidades, presentándose un faltante de 16 unidades, las cuales se encuentran pendientes de envío por parte de ustedes. Adicionalmente, se solicita su amable colaboración respecto a la unidad de empaque, dado que se evidenció que algunos paquetes indicaban contener 50 unidades, información que no correspondía con el contenido real. | J39: PRODUCTO NO CONFORME | K39: SI | L39: MAYOR | M39: PRODUCCIÓN Y DIRECCIÓN TÉCNICA | N39: MARTINEZ GRANADOS MARIA VICTORIA | Q39: ABIERTA | S39: ABIERTA | T39: SERVICIO AL CLIENTE | U39: ANDREA CHANTRE AUX FARMACIA | V39: 3168785821 | W39: auxmedicamentoshuv@farmartips.com | X39: ADJUNTOS | Y39: NO
A40: 1 | B40: 36 | C40: 46051 | D40: ENERO | E40: CUNDINAMARCA | F40: CHRISTUS SINERGIA | G40: CHRISTUS SINERGIA | H40: SOLIDOS | I40: Buen día, Espero se encuentren muy bien. El día de ayer, 02/02/2026, se evidenció un retraso aproximado de una hora, el cual no fue informado oportunamente, tal como se establece en el contrato. Debido a esta falta de notificación, no fue posible alertar a los diferentes servicios sobre la tardanza en la entrega de las adecuaciones. Es importante dar estricto cumplimiento a los horarios de llegada, ya que este tipo de retrasos puede generar afectaciones en la administración de medicamentos y comprometer la seguridad del paciente. Adicionalmente, durante la mañana se realizó la solicitud de algunas adecuaciones requeridas por pacientes, las cuales no fueron entregadas dentro de las adecuaciones recepcionadas el día de ayer. Agradecemos se tomen las medidas necesarias para evitar la recurrencia de estas situaciones y se dé cumplimiento a lo establecido. Quedamos atentos a sus comentarios. | J40: PRODUCTO NO CONFORME | K40: SI | L40: MAYOR | M40: PRODUCCIÓN Y DIRECCIÓN TÉCNICA | N40: MARTINEZ GRANADOS MARIA VICTORIA | Q40: ABIERTA | S40: ABIERTA | T40: SERVICIO AL CLIENTE | U40: YESICA ALEJANDRA GOEZ PUENTES | V40: N/R | W40: quimicofarmaceutico2.cpr@christus.co | X40: ADJUNTOS | Y40: NO
A41: 1 | B41: 37 | C41: 46063 | D41: FEBRERO | E41: OCCIDENTE | F41: FUND CLINICA INFANTIL CLUB NOEL | G41: FUND CLINICA INFANTIL CLUB NOEL | H41: ONCOLOGÍA | I41: El día de hoy se nos presenta la siguiente novedad. Al recibir los dos preparados de la Quimioterapia Intratecal, la compañera Regente Maria Eugenia refiere que vienen marcados con el mismo nombre del paciente ( Janer Arley Gomez) motivo por el cual se hace devolución del preparado para realizar los determinados ajustes. Se recibe de nuevo el preparado al validar por parte de la Regente Maria Eugenia viene con el cambio en la rotulación de la etiqueta externa del paciente (Rene Andrés Angulo), sin embargo en el servicio de Infusiones al destapar la bolsa observan que la rotulación de la jeringa también presenta fallas en la rotulación (ver archivo anexo), motivo por el cual por seguridad no se puede administrar al paciente. Dado lo anterior solicito el favor de tan amable realizar un plan de acción para evitar que nos vuelva a suceder estos sucesos que arriesgan la seguridad de nuestros pacientes. | J41: ERROR EN ETIQUETA/CODIFICADO | K41: SI | L41: MAYOR | M41: PRODUCCIÓN Y DIRECCIÓN TÉCNICA | N41: MARTINEZ GRANADOS MARIA VICTORIA | Q41: ABIERTA | S41: ABIERTA | T41: SERVICIO AL CLIENTE | U41: Lina Maria Muñoz Fernandez Química Farmacéutica de Oncología | V41: Tel: 602 485 44 04 Ext.: 1128 | W41: qf.oncologico@fciclubnoel.com | X41: ADJUNTOS | Y41: NO
A42: 1 | B42: 38 | C42: 46064 | D42: FEBRERO | E42: EJE CAFETERO | F42: HOSPITAL UNIVERSITARIO SAN JORGE PEREIRA | G42: HOSPITAL UNIVERSITARIO SAN JORGE DE PEREIRA | H42: DOSIS ANTICIPADA | I42: Buenos días, Por medio del presente correo me permito informar un error identificado y reportado al servicio farmacéutico el día de hoy, 2 de febrero de 2026, relacionado con el proceso de unidosis de Insulinas. Aunque en el empaque de una insulina se encontraba rotulada la dosis de insulina glargina 6 UI, al revisar el contenido antes de su administración, se evidenció que la jeringa incluida correspondía a una jeringa de 10 UI. El error fue detectado de manera oportuna previo a la administración del medicamento, momento en el cual el personal asistencial informó inmediatamente la situación al servicio farmacéutico, evitando así un posible error de medicación. Posteriormente, se realizó la verificación del insumo correcto y el ajuste correspondiente para garantizar la seguridad del paciente. Agradezco y solicito respetuosamente que, por favor, se realice una revisión del proceso, con el fin de identificar oportunidades de mejora y prevenir la ocurrencia de errores similares en el futuro, fortaleciendo así la seguridad del paciente. Quedo atenta a las indicaciones y acciones que consideren pertinentes. Adjunto evidencia. Buena tarde. A continuación adjunto respuesta de los reportes de PQRS realizados por su parte en las fechas 11/02/26,20/02/26,02/03/26, 04/03/2026, a las cuáles no se les había dado respuesta, ya que se decidió unir todas las quejas con el fin de hacer un solo análisis de causas y emitir una sola respuesta en general, teniendo en cuenta que las novedades se presentaron básicamente en el mismo proceso de Calidad ( Empaque, liberación de producto terminado y liberación de etiquetas) por situaciones del personal responsable. Agradecemos sus reportes oportunos de novedades, desviaciones o no conformidades que se presenten en los procesos, teniendo en cuenta que debemos trabajar en equipo y de la mano cliente/proveedor, para mantener una mejora continua de los procesos, garantizando con ello la seguridad de los pacientes, por medio de productos finales conformes con todos los requisitos y atributos de calidad solicitados por el cliente y exigidos por la normativa vigente. Quedamos atentos a cualquier duda o solicitud adicional. | J42: ERROR EN ETIQUETA/CODIFICADO | K42: SI | L42: MAYOR | M42: PRODUCCIÓN Y DIRECCIÓN TÉCNICA | N42: RICO GIL LEIDY BIBIANA | Q42: ABIERTA | S42: ABIERTA | T42: SERVICIO AL CLIENTE | U42: Manuela González Lanzas Jefe técnico SDMDU HUSJ | V42: 3105474457 | W42: director.unidosis@husj.gov.co | X42: ADJUNTOS | Y42: NO
A43: 1 | B43: 39 | C43: 46065 | D43: FEBRERO | E43: CUNDINAMARCA | F43: HOSPITAL UNIVERSITARIO CLINICA SAN RAFAEL | G43: HOSPITAL U SAN RAFAEL BOGOTA | H43: DOSIS ANTICIPADA | I43: "Se interpone una queja dado que el día 05/02/2026 se envía solicitud para preparación de lotes de medicamentos de control especial indicando que se requiere preparar de manera urgente. Sin embargo, al día de hoy 12/02/2026, no se han recibido las adecuaciones ni se generó respuesta al correo de solicitud. Es importante tener en cuenta que no se están enviando a preparar lotes de antibióticos, por lo cual debería agilizarse el proceso con las demás solicitudes. Adjunto evidencia del correo con la solicitud. " | J43: ENTREGA FUERA DEL ACUERDO DE SERVICIO | K43: SI | L43: MAYOR | M43: PRODUCCIÓN Y DIRECCIÓN TÉCNICA | N43: MARTIN DURANGO | Q43: ABIERTA | S43: ABIERTA | T43: SERVICIO AL CLIENTE | U43: Neyla Quintana Ariza - Química Farmacéutica | V43: 328 23 00 Extensión - 2814 | W43: mailto:neyla.quintana@stewardcolombia.org | X43: ADJUNTOS | Y43: NO
A44: 1 | B44: 40 | C44: 46065 | D44: FEBRERO | E44: MARLY CUNDINAMARCA | F44: CLINICA DE MARLY S.A. | G44: CLINICA DE MARLY BOGOTA | H44: DOSIS ANTICIPADA | I44: "El día 10 de febrero se solicita la preparación de un lote de 80 unidades de oxicodona de 3 mg en donde se solicita que las etiquetas contengan la información correcta sobre el medicamento. Al ser recepcionadas el día 11/02/2026 con el número de despacho 484664, lote RM26121754 Y FV. 10/03/2026; se evidencia que la etiqueta del medicamento cuenta con el código incorrecto para el medicamento (CÓD. 78363). Cabe aclarar que durante la orden de producción se hizo una previa revisión y en esta misma se solicitó con el código 78369. Tras esto se procede a revisar los lotes anteriores si se ha presentado el mismo problema por lo cual se identifica que la producción de la semana del 27/01/2026 con numero de pedido 480781 y lote del medicamento RM2678241, igualmente presento el código incorrecto. Agradecemos su colaboración en la revisión de esta situación. " | J44: ERROR EN ETIQUETA/CODIFICADO | K44: SI | L44: MAYOR | M44: PRODUCCIÓN Y DIRECCIÓN TÉCNICA | N44: RUBER VALECILLOS | Q44: ABIERTA | S44: ABIERTA | T44: SERVICIO AL CLIENTE | U44: DANIELA GASCA - QUIMICA FARMACEUTICA | V44: 3436600 EXT 2502 | W44: esteriles.farmacia@clinicademarly.com.co | X44: ADJUNTOS | Y44: NO
A45: 1 | B45: 41 | C45: 46065 | D45: FEBRERO | E45: CUNDINAMARCA | F45: HOSPITAL UNIVERSITARIO SAN IGNACIO | G45: HOSPITAL UNIVERSITARIO SAN IGNACIO | H45: ESTERILES | I45: Cordial saludo El presente con el fin de reportar queja en cuanto al retraso en entrega de las dosis unitarias de estériles del día 10 de febrero las cuales se recibieron a las 18:25 (horario pactado 17:00). Adjunto envío documento. Agradezco la atención prestada y quedo atenta a comentarios. Quedo atenta a cualquier inquietud. | J45: ENTREGA FUERA DEL ACUERDO DE SERVICIO | K45: SI | L45: MAYOR | M45: PRODUCCIÓN Y DIRECCIÓN TÉCNICA | N45: MARTIN DURANGO | O45: 46094 | P45: 46094 | Q45: CERRADA | S45: ABIERTA | T45: SERVICIO AL CLIENTE | U45: Luisa Ovalle Químico Farmacéutico Asistencial | V45: Teléfono: (601) 5946161 Ext. 3007 | W45: luovalle@husi.org.co | X45: ADJUNTOS | Y45: NO
A46: 1 | B46: 42 | C46: 46065 | D46: FEBRERO | E46: CUNDINAMARCA SOLIDOS | F46: CLINICA UNIVERSIDAD DE LA SABANA | G46: CLINICA UNIVERSITARIA DE LA SABANA | H46: SOLIDOS | I46: Cordial saludo, Por medio de la presente nos permitimos notificar una desviación de calidad evidenciada en el proceso de reempaque del medicamento Metadona 10 mg, lote 250502-09, con fecha de vencimiento 05/2027. Se verificaron las recepciones técnicas del empaque primario desde el momento de su ingreso al Servicio Farmacéutico el día 10 de noviembre de 2025. Las unidades fueron revisadas una a una tanto por el auxiliar de farmacia como por el regente de farmacia, dejando constancia de conformidad en cantidad y condiciones físicas. Posteriormente, el medicamento fue enviado al área de adecuación con su respectiva orden de producción el día 15/11/2025, donde se realizó nuevamente la verificación física de las unidades y la validación de los datos remitidos para el proceso de reempaque. El día 28/11/2025 se recibió el medicamento debidamente sellado, confirmando con el regente de farmacia la revisión del empaque de las unidades provenientes de la central de mezclas. No obstante, debido a la rotación de inventario, el día de ayer, al momento de alistar los medicamentos de control especial para entrega al personal del turno, se evidenció que una de las unidades se encontraba completamente sellada, sin signos de manipulación ni fuga, pero sin contener la tableta en su interior. Dado que se trata de un medicamento de control especial, esta situación constituye una desviación grave dentro de los procesos de aseguramiento de calidad establecidos en la central de mezclas. Por lo anterior, solicitamos de manera prioritaria su análisis técnico y respuesta formal frente a esta desviación, incluyendo el concepto de calidad correspondiente y el plan de acción a implementar. Esta información se requiere con carácter urgente, considerando la próxima visita del Fondo Nacional de Estupefacientes a las instalaciones de la clínica, con el fin de soportar adecuadamente este faltante, el cual no fue reportado previamente por la central de mezclas. Adjunto soportes Agradecemos su pronta atención y quedamos atentos a su respuesta formal. Atentamente, | J46: PRODUCTO NO CONFORME | K46: SI | L46: MAYOR | M46: PRODUCCIÓN Y DIRECCIÓN TÉCNICA | N46: DORIA NARVÁEZ REYES ENRIQUE | O46: 46093 | P46: 46093 | Q46: CERRADA | S46: ABIERTA | T46: SERVICIO AL CLIENTE | U46: SNEHIA MENDOZA | V46: 8617777 | W46: sanehia.mendoza@clinicaunisabana.edu.co | X46: ADJUNTOS | Y46: NO
A47: 1 | B47: 43 | C47: 46066 | D47: FEBRERO | E47: CUNDINAMARCA | F47: SURAMERICANA IPS SERVICIOS SALUD | G47: SURAMERICANA IPS SERVICIOS SALUD | H47: ESTERILES | I47: Buena tarde. Señores unidosis reporto la novedad de bomba elastomerica de CEFEPIME 3000 MG el cual salió auxiliar enfermera el día de hoy para su administración en domicilio, pero esta presenta fuga de líquido o se trasvaso completamente. Recordar que es evento adverso para el paciente esperamos pronta respuesta . | J47: PRODUCTO NO CONFORME | K47: SI | L47: MAYOR | M47: PRODUCCIÓN Y DIRECCIÓN TÉCNICA | N47: MARTIN DURANGO | Q47: ABIERTA | S47: ABIERTA | T47: SERVICIO AL CLIENTE | U47: William Ospina Cifuentes Aux Farmacia Salud en casa | V47: N/R | W47: wospinac@sura.com.co | X47: ADJUNTOS | Y47: NO
A48: 1 | B48: 44 | C48: 46066 | D48: FEBRERO | E48: CUNDINAMARCA | F48: CLINICA JUAN N CORPAS | G48: CLINICA JUAN N CORPAS | H48: SOLIDOS | I48: LOTE 25B232 ACETAMINOFEN DE 500 ID 0130001393 SEGÚN IMAGEN FOTOGRAFICA VIENE SIN UNA TABLETA | J48: PRODUCTO NO CONFORME | K48: SI | L48: MAYOR | M48: PRODUCCIÓN Y DIRECCIÓN TÉCNICA | N48: DORIA NARVÁEZ REYES ENRIQUE | Q48: ABIERTA | S48: ABIERTA | T48: SERVICIO AL CLIENTE | U48: John Edwin Fajardo R. Q.F. Servicio Farmacéutico CJNC | V48: N/R | W48: quimico_farmaceutico@clinicajuanncorpas.com | X48: ADJUNTOS | Y48: NO
A49: 1 | B49: 45 | C49: 46069 | D49: FEBRERO | E49: CUNDINAMARCA SOLIDOS | F49: CLÍNICA CENTENARIO S.A.S | G49: CLINICA CENTENARIO | H49: SOLIDOS | I49: Buenas tardes. Envió evidencia donde se encuentra mal rotulado carvedilol de 12,5 mg por carvedilol de 25 mg . Agradecemos su colaboración con la verificación y correcta liberación de los productos ya que esto puede generar errores de medicación y complicaciones mayores. | J49: ERROR EN ETIQUETA/CODIFICADO | K49: SI | L49: MAYOR | M49: PRODUCCIÓN Y DIRECCIÓN TÉCNICA | N49: DORIA NARVÁEZ REYES ENRIQUE | Q49: ABIERTA | S49: ABIERTA | T49: SERVICIO AL CLIENTE | U49: JAIME AGUILAR RODRIGUEZ | V49: 74601111405 | W49: regente.bodega@stewardcolombia.org | X49: ADJUNTOS | Y49: NO
A50: 1 | B50: 46 | C50: 46069 | D50: FEBRERO | E50: OCCIDENTE | F50: FUND CLINICA INFANTIL CLUB NOEL | G50: FUND CLINICA INFANTIL CLUB NOEL | H50: ESTERILES | I50: El día de hoy se nos presenta la siguiente novedad. Al recibir los dos preparados de la Quimioterapia Intratecal, la compañera Regente Maria Eugenia refiere que vienen marcados con el mismo nombre del paciente ( Janer Arley Gomez) motivo por el cual se hace devolución del preparado para realizar los determinados ajustes. Se recibe de nuevo el preparado al validar por parte de la Regente Maria Eugenia viene con el cambio en la rotulación de la etiqueta externa del paciente (Rene Andrés Angulo), sin embargo en el servicio de Infusiones al destapar la bolsa observan que la rotulación de la jeringa también presenta fallas en la rotulación (ver archivo anexo), motivo por el cual por seguridad no se puede administrar al paciente. Dado lo anterior solicito el favor de tan amable realizar un plan de acción para evitar que nos vuelva a suceder estos sucesos que arriesgan la seguridad de nuestros pacientes. - | J50: PRODUCTO NO CONFORME | K50: SI | L50: MAYOR | M50: PRODUCCIÓN Y DIRECCIÓN TÉCNICA | N50: ANGELA MARCELA PARRA ESPITIA | Q50: ABIERTA | S50: ABIERTA | T50: SERVICIO AL CLIENTE | U50: Andrea Liliana Tolosa Riveros Jefe de Servicio Farmacéutico | V50: Tel: 602 485 44 04 Ext.: 1189 | W50: ervicio.farmaceutico@fciclubnoel.com | X50: ADJUNTOS | Y50: NO
A51: 1 | B51: 47 | C51: 46069 | D51: FEBRERO | E51: LLANOS | F51: NUEVA CLINICA EL BARZAL SAS | G51: NUEVA CLINICA EL BARZAL SAS | H51: TODAS | I51: Estimados, Reciban un cordial saludo. Por medio del presente, nos permitimos manifestar nuestra inconformidad respecto a los tiempos de notificación relacionados con la no disponibilidad de insumos utilizados en la preparación de nutriciones parenterales. De manera reiterada hemos recibido notificaciones con un margen de apenas 24 horas informando que ya no cuentan con determinado insumo. Esta situación nos obliga a realizar ajustes inmediatos en la prescripción por parte del profesional de nutrición, lo que a su vez genera reprocesos internos, sobrecarga operativa y posibles retrasos en la atención de los pacientes. Consideramos que este tipo de avisos con tan poca antelación impacta de manera directa la planeación asistencial y los procesos clínicos de nuestra institución. Por tal motivo, presentamos formalmente esta inconformidad, la cual ha sido manifestada también por la Dirección Asistencial, y solicitamos se revisen y fortalezcan los mecanismos de comunicación y anticipación frente a posibles desabastecimientos. Agradecemos su atención a la presente y quedamos atentos a sus comentarios y a las acciones de mejora que puedan implementarse para evitar que esta situación continúe presentándose. Cordialmente, | J51: INCUMPLIMIENTO ACTIVIDADES O COMPROMISOS | K51: SI | L51: MAYOR | M51: PRODUCCIÓN Y DIRECCIÓN TÉCNICA | N51: TATIANA RICO | Q51: ABIERTA | S51: ABIERTA | T51: SERVICIO AL CLIENTE | U51: Karen Gutierrez Valderrama Quimica Farmaceutica | V51: Tel: 6726521 Ext. 1235 | W51: farmacia@ncbsas.com | X51: ADJUNTOS | Y51: NO
A52: 1 | B52: 48 | C52: 46071 | D52: FEBRERO | E52: CUNDINAMARCA | F52: FUNDACION HOSPITAL SAN CARLOS | G52: FUNDACION HOSPITAL SAN CARLOS BOGOTA | H52: INCUMPLIMIENTO DE A | I52: Cordial saludo señores Unidosis, Por medio del presente nos permitimos informar las novedades identificadas en las últimas semanas relacionadas con las entregas de adecuaciones de medicamentos de control especial, así como el impacto que estas están generando en la operación del Servicio Farmacéutico y en la atención segura de los pacientes de la Fundación Hospital San Carlos. De acuerdo con el seguimiento realizado por el referente de farmacovigilancia institucional a la Orden de Producción OP 23-01-2026, se evidencian las siguientes situaciones: No se está cumpliendo con la entrega del 100% de las adecuaciones solicitadas. Transcurridos veinte (20) días desde el envío de la orden, aún se encuentran pendientes adecuaciones por entregar. La no disponibilidad oportuna de estas preparaciones ha generado afectaciones directas en: Oportunidad en la administración de medicamentos a los pacientes, comprometiendo la continuidad terapéutica. Reprocesos operativos, debido a la necesidad de coordinar modificaciones de formulación con el equipo médico. Sobrecarga administrativa y asistencial, generando insatisfacción en el equipo clínico y aumento de tiempos no productivos. Adicionalmente, esta situación está generando riesgos clínicos y operativos relevantes, entre ellos: Desperdicio de medicamento y pérdida de remanentes al no contar con dosis ajustadas. Mayor riesgo de errores de medicación al requerir manipulaciones o fraccionamientos no previstos. Incremento del riesgo de pérdida o desvío de medicamentos de control especial al no disponer de presentaciones adecuadas en dosis unitaria. Riesgo de eventos adversos asociados a ajustes improvisados de dosis. Impacto financiero por aumento del gasto institucional y baja eficiencia en el uso de recursos. Riesgo normativo por incumplimiento de lineamientos del INVIMA y del Fondo Nacional de Estupefacientes en cuanto a adecuación, trazabilidad y entrega en condiciones que garanticen seguridad y control. En el marco del Sistema de Gestión de Calidad y del Programa de Seguridad del Paciente, esta situación constituye una alerta operacional relevante, al tratarse de medicamentos de control especial cuyo manejo exige oportunidad, trazabilidad y estricta adherencia normativa. A la fecha de este correo se han enviado dos (2) quejas formales del día 28-11-2025 y 08-01-2026 en formato AC-FR-054-04 ATENCION Y SEGUIMIENTO DE PQRS definido por unidosis para la presentación de las mismas, sin tener una respuesta a la fecha. En ese orden de ideas y teniendo en cuenta la gravedad de lo expuesto, solicitamos de manera formal: Dar respuesta a las quejas presentadas y adjuntas en este correo. Informe de las causas del incumplimiento en la OP 23-01-2026. Cronograma claro y definitivo de entrega de las adecuaciones pendientes. Plan de acción inmediato que garantice la no repetición de esta situación en futuras órdenes de producción. Agradecemos su pronta respuesta y las acciones correctivas correspondientes, teniendo en cuenta el impacto asistencial y normativo que esta situación está generando. | J52: INCUMPLIMIENTO DE ACTIVIDADES O COMPROMISOS | K52: SI | L52: MAYOR | M52: PRODUCCIÓN Y DIRECCIÓN TÉCNICA | N52: MARTIN DURANGO | Q52: CERRADA | S52: ABIERTA | T52: SERVICIO AL CLIENTE | U52: JUAN CARLOS CORONEL DUARTE | V52: 7443333 | W52: jcoronel@fhsc.org.co | X52: ADJUNTOS | Y52: NO
A53: 1 | B53: 49 | C53: 46071 | D53: FEBRERO | E53: CUNDINAMARCA SOLIDOS | F53: ZENTRIA AVIDANTI | G53: AVIDANTE BUS HOSPITAL DEL NORTE | H53: SOLIDOS | I53: Buenos días, Por medio del presente informo novedad relacionada con el pedido recibido de Unidossis el pasado 19/01/2026, bajo la orden N° 4115N. En dicho pedido se solicitó el reempaque de Amlodipino 5 mg, lote F02254A, fecha de vencimiento 09/2027, por un total de 1.800 unidades. El día de hoy, al momento de realizar la dispensación, se identificaron 2 unidades del producto cuyo empaque se encuentra totalmente sellado, pero vacío, sin tabletas en su interior (adjunto evidencia fotográfica). Solicito por favor se escale el caso a Unidossis para documentar la novedad, con el fin de gestionar la respectiva respuesta y proceder con la baja de estas unidades en nuestro sistema de información. Quedo atenta a las indicaciones y al soporte correspondiente para cerrar el caso. Muchas gracias. | J53: ERROR DE EMPAQUE | K53: SI | L53: MAYOR | M53: PRODUCCIÓN Y DIRECCIÓN TÉCNICA | N53: DORIA NARVÁEZ REYES ENRIQUE | Q53: ABIERTA | S53: ABIERTA | T53: SERVICIO AL CLIENTE | U53: CARLOS JOSE IRARTE ROSA | V53: 3188142323 | W53: carlos.iriarte@zentria.com.co | X53: ADJUNTOS | Y53: NO
A54: 1 | B54: 50 | C54: 46071 | D54: FEBRERO | E54: CUNDINAMARCA SOLIDOS | F54: SOCIEDAD DE CIRUGIA DE BOGOTA HOSPITAL DE SAN JOSE | G54: HOSPITAL DE SAN JOSE | H54: NPT | I54: "Buenos dias. Con el presente documento quiero notificar que para el 15/025/2026 se terminaron las NPT de los pacientes Maria Elena Sanchez Herrera a las 16:30hrs y Yeisonn Jair Acuña Rodriguez a las 17:00hrs, aproximadamente 1:30h antes de lo esperado ya que se inicia la administración a las 19:00hrs , se realiza verificación a la programación de la bomba encontrando coincidencia entre lo indicado y lo programado, no es claro el motivo detrás de la terminación anticipada del producto, esta situación se ha presentado previamente y de forma reiterativa. Esta situación aumenta el riesgo en la prestación de servicios de salud al no garantizar el tiempo de administración, adicionalmente, esta situación preocupa al generar dudas sobre la composición del producto terminado que pueden afectar el aporte nutricional diario al no alcanzar la meta calórica propuesta, los servicios expresan preocupación frente a este hecho pues deben tomar medidas ante la terminación anticipada del producto. Dado lo anterior, se le solicita atentamente a Unidossis realice un informe aclarando lo sucedido y un plan de mejora con el fin de evitar que se repitan estas situaciones anteriormente descritas." | J54: PRODUCTO NO CONFORME | K54: SI | L54: MAYOR | M54: PRODUCCIÓN Y DIRECCIÓN TÉCNICA | N54: MARTIN DURANGO | Q54: ABIERTA | S54: ABIERTA | T54: SERVICIO AL CLIENTE | U54: Juana Vargas , Químico Farmacéutico | V54: 3538000 Ext. 468 | W54: rordenespro20211123@gmail.com | X54: ADJUNTOS | Y54: NO
A55: 1 | B55: 51 | C55: 46071 | D55: FEBRERO | E55: CUNDINAMARCA SOLIDOS | F55: FUNDACION ABOOD SHAIO | G55: FUND SHAIO | H55: SOLIDOS | I55: Buen día, Durante el proceso de recepción técnica de la tabletería enviada para reempaque, se identificaron averías en medicamentos de alto costo y, en el caso de los medicamentos que no son de alto costo, un número de unidades superior al porcentaje permitido por cada referencia reempacada; las averías corresponden a las OP de tabletería enviadas después de la última solicitud de nota crédito (01-12-2025). Por lo anterior, solicito amablemente la emisión de la nota crédito correspondientes a los siguientes ítems: Medicamentos no alto costo (número de unidades superior al porcentaje permitido por cada orden de producción):  Código Descripción Unidades Vr unitario 17014345 TAMSULOSINA 0.4MG CAP LIB MOD 23 $ 295 17400821 ACETAMINOFEN 500 MG TAB 42 $ 40 17400102 ACETILSALICILICO ACIDO 100MG TAB 17 $ 1.033 17003153 CICLOSPORINA 25MG CAP 2 $ 2.101 17016420 CLOPIDOGREL 75MG TAB 12 $ 118 17340381 DIMENHIDRINATO 50MG TAB 3 $ 680 17280587 FENITOINA 100MG CAP 1 $ 495 17902149 CAPTOPRIL 25MG TAB 1 $ 69 17004713 ESomeprazol 20 mg TAB 7 $ 90 17011698 LEVETIRACETAM 500MG TAB 2 $ 1.463 17002551 NIFEdipino 30 mg TAB LIB PROGR 5 $ 217 17012671 VALSARTAN TAB RECUBIERTA 80MG 19 $ 700 17666785 NIMODIPINO 30MG TAB 3 $ 160 17006189 PREGABALINA 75MG CAPSULA DURA 3 $ 898 17350463 SUCRALFATE 1G TAB 4 $ 450 17016311 QUETIAPINA 25MG TABLETA RECUBIERTA 1 $ 128 17191446 prednisoLONA 5 mg TAB 1 $ 47 17646464 LEVOTIROXINA 50MCG TAB 6 $ 39 17008762 ATORVASTATINA 40MG TAB 1 $ 112 Medicamentos alto costo:  Código Descripción Unidades Vr unitario 17013440 SILDENAFILO CITRATO 20MG TAB 7 $ 18.000 17013734 DAPAGLIFLOZINA 10MG COMPRIMIDO RECUBIERTO 2 $ 4.900 17180787 MICOFENOLATO MOFETILO 500MG TAB 1 $ 6.863 17005403 TACROLIMUS 1MG CAP LIBERACION PROLONGADA 2 $ 6.150 17310244 CICLOSPORINA 50MG CAP 1 $ 4.055 17213407 SACUBITRILO/VALSARTAN 24.3MG+25.7MG (50MG) TAB RECUBIERTA 3 $ 4.226 17008296 MICOFENOLATO SODICO 360MG TAB 1 $ 5.200 17213421 SACUBITRILO/VA | J55: DIFERENCIA EN INVENTARIO EN CUSTODIA | K55: SI | L55: MAYOR | M55: PRODUCCIÓN Y DIRECCIÓN TÉCNICA | N55: DORIA NARVÁEZ REYES ENRIQUE | Q55: ABIERTA | S55: ABIERTA | T55: SERVICIO AL CLIENTE | U55: Oscar Alfonso Vargas Bautista Químico(a) Farmacéutico(a) | V55: PBX (601) 593 8210 | W55: alfonso.vargas@shaio.org | X55: ADJUNTOS | Y55: NO
A56: 1 | B56: 52 | C56: 46072 | D56: FEBRERO | E56: CUNDINAMARCA | F56: SOCIEDAD DE CIRUGIA DE BOGOTA HOSPITAL DE SAN JOSE | G56: HOSPITAL DE SAN JOSE | H56: ONCOLOGÍA | I56: El día martes 17 de Febrero a las 11:40am se envió la solicitud de orden de producción de oncologicos jornada mañana URGENTE 2, la cual contenia 2 (dos) quimioterapias, que debian llegar a las 2:10pm; Sin embargo la quimioterapia llega a las 4:00pm, es decir, con un retraso de 1 hora y 50 minutos, incumpliendo el acuerdo de servicios por parte de ustedes. Por este inconveniente presentado el Hospital San José en el servicio de HEMATOLOGIA HOSPITALIZACIÓN se incumplió con el horario de aplicación de los medicamentos, afectando a nuestros pacientes; solicito pronta respuesta aclarando lo sucedido y evaluar que medidas adicionales o planes de mejora se pueden implementar para evitar este tipo de inconvenientes. | J56: DIFERENCIA EN INVENTARIO EN CUSTODIA | K56: SI | L56: MAYOR | M56: PRODUCCIÓN Y DIRECCIÓN TÉCNICA | N56: DORIA NARVÁEZ REYES ENRIQUE | Q56: ABIERTA | S56: ABIERTA | T56: SERVICIO AL CLIENTE | U56: LORENA CASTILLO - QUIMICA FARMACEUTICA | V56: 3538000 Ext. 468 | W56: mailto:centraldemezclas@hospitaldesanjose.org.co | X56: ADJUNTOS | Y56: NO
A57: 1 | B57: 53 | C57: 46073 | D57: FEBRERO | E57: MARLY CUNDINAMARCA | F57: CLINICA DE MARLY S.A. | G57: CLINICA DE MARLY BOGOTA | H57: ONCOLOGÍA | I57: "El día viernes 20 de febrero de 2026 se envia orden de producción de Cisplatino para el paciente CAMILO ANDRES GONZALEZ SUAREZ, dosis 49 mg, diluida en SSN 0,9% de 250 mL para volumen final de 299 mL. Sobre las 9 de la mañana se notifica que se preparó la mezcla accidentalmente con la DAD 5% de 500 mL que se entregó para la preparación de otro medicamento. Al revisar el inserto del medicamento indica ""No diluir Cisplatino solo en DAD 5%"", y al revisar literatura se indica que el cisplatino debe diluirse en soluciones con una concentración de cloruro de al menos 0,45%, de otro modo el medicamento se degrada. No se hace claridad en literatura del tiempo de estabilidad en DAD 5% unicamente, por lo que es necesario desechar la mezcla y preparar una nueva con un nuevo vial de cisplatino, y de esta manera entregar a tiempo el medicamento al paciente. Se solicita la revisión el caso, envío de análisis causa-raiz y la devolución del medicamento e insumos." | J57: PRODUCTO NO CONFORME | K57: SI | L57: MAYOR | M57: PRODUCCIÓN Y DIRECCIÓN TÉCNICA | N57: DORIA NARVÁEZ REYES ENRIQUE | Q57: ABIERTA | S57: ABIERTA | T57: SERVICIO AL CLIENTE | U57: DANIELA GASCA PARRADO JULIANA ROJAS CASTAÑEDA Química Farmacéutica - UEB Química Farmacéutica - UNAL | V57: 601-3436600 - Ext. 2502 | W57: esteriles.farmacia@clinicademarly.com.co | X57: ADJUNTOS | Y57: NO
A58: 1 | B58: 54 | C58: 46073 | D58: FEBRERO | E58: EJE CAFETERO | F58: HOSPITAL UNIVERSITARIO SAN JORGE PEREIRA | G58: HOSPITAL UNIVERSITARIO SAN JORGE DE PEREIRA | H58: ONCOLOGÍA | I58: Buenos días, Por medio del presente informo inconsistencias identificadas en dosis unitarias recibidas el día fin de semana: Se recibió una jeringa rotulada como CAFEÍNA, contenida en un empaque secundario cuyo rótulo corresponde a CEFEPIME, evidenciando discordancia entre el medicamento preparado y el empaque externo. En otra unidad se identificó que ni el nombre del paciente ni la dosis consignada en la jeringa coinciden con la información registrada en el empaque secundario, constituyendo una inconsistencia crítica. Estas situaciones representan un riesgo significativo para la seguridad del paciente y podrían derivar en un evento adverso si no se detectan oportunamente antes de la administración. Solicito de manera prioritaria la revisión del proceso de preparación, rotulado y verificación final antes del despacho, así como el envío de un plan de mejora con acciones correctivas y preventivas, orientado a evitar la recurrencia de este tipo de eventos. Quedo atenta a su pronta respuesta. Cordialmente, | J58: PRODUCTO NO CONFORME | K58: SI | L58: MAYOR | M58: PRODUCCIÓN Y DIRECCIÓN TÉCNICA | N58: RICO GIL LEIDY BIBIANA | Q58: ABIERTA | S58: ABIERTA | T58: SERVICIO AL CLIENTE | U58: Manuela González Lanzas Jefe técnico SDMDU HUSJ | V58: 3105474457 | W58: director.unidosis@husj.gov.co | X58: ADJUNTOS | Y58: NO
A59: 1 | B59: 55 | C59: 46073 | D59: FEBRERO | E59: EJE CAFETERO | F59: SOCIEDAD DE CIRUGIA DE BOGOTA HOSPITAL DE SAN JOSE | G59: HOSPITAL DE SAN JOSE | H59: ONCOLOGÍA | I59: El día viernes 20 de Febrero se envio la solicitud de orden de producción de oncologia urgente - Jornada Tarde, en esta orden de producción se encontraban dos mezclas de Rituximab (100mg en 100ml SSN y 600mg en 600ml SSN respectivamente) de la paciente MARTHA CATALINA ZULUAGA MAYAdel servicio de hematologia hospitalización; Sin embargo al realizar la recepción técnica de las mezclas oncologicas la Regente de Farmacia de la farmacia central del Hospital evidencia que las mezcla oncologica vienen con las etiquetas primarias y secudandarias incorrectas, es decir, la bolsa de 100ml de SSN tiene la etiqueta pegada de Rituximab 600mg en 600ml SSN y la bolsa de SSN de 1000ml tiene pegada la etiqueta de Rituximab 100mg en 100ml SSN; ademas esta ultima bolsa que en realidad contiene Rituximab 600mg (1 vial 100mg/10ml SOL INY y 1 vial 500mg/50ml SOL INY) en 600ml se viene regando y parte del contenido de la misma se encuentra en la bolsa trasparente del empaque primario y en la bolsa azul del empaque secundario. Se procede a rechazar las mezclas y devolver las misma con el trasportador a UNIDOSSIS SAS, de igual manera se informa a QF Martin del área de interpretación lo ocurrido para que procedan con la preparación de una nueva mezcla, el cambio de las etiquetas respectivamente y el envio Urgente de las mismas a la Sociedad de Cirugia de Bogotá Hospital de San José. Por este inconveniente presentado el Hospital San José en el servicio de HEMATOLOGIA HOSPITALIZACION se incumplió con el horario de aplicación del medicamento, afectando a nuestra paciente; Adicionalmente requerimos reposición prioritaria en nuestro inventario de los viales faltantes de Rituximab (1 vial 100mg/10ml SOL INY y 1 vial 500mg/50ml SOL INY) de laboratorios Abbott. Quedamos atentos a su pronta respuesta y esperamos que situaciones como estas no se vuelvan a presentar. (Se adjunta a correo electronico imagen donde se puede evidenciar lo descrito anteriormente) | J59: PRODUCTO NO CONFORME | K59: SI | L59: MAYOR | M59: PRODUCCIÓN Y DIRECCIÓN TÉCNICA | N59: MARTIN DURANGO | Q59: ABIERTA | S59: ABIERTA | T59: SERVICIO AL CLIENTE | U59: LORENA CASTILLO - QUIMICA FARMACEUTICA | V59: 3538000 Ext. 468 | W59: centraldemezclas@hospitaldesanjose.org.co | X59: ADJUNTOS | Y59: NO
A60: 1 | B60: 56 | C60: 46073 | D60: FEBRERO | E60: EJE CAFETERO | F60: CLINICA UNIVERSIDAD DE LA SABANA | G60: CLINICA UNIVERSITARIA DE LA SABANA | H60: DOSIS ANTICIPADA | I60: Buen día, Mediante el presente reporto, el día de ayer recibimos la orden de producción 486838 correspondiente a 200 JP de hidromorfona lote: RC26146217, y al realizar la inspección de calidad, se evidencia un empaque con doble jeringa. Solicitamos una revisión de lo ocurrido. Asimismo, agradecemos nos informen las medidas correctivas que se implementarán para evitar que estos errores se repitan. Además, quedo atenta para saber como proceder con la unidad, si nos suministraran el empaque secundario o si se realiza destrucción de la misma | J60: PRODUCTO NO CONFORME | K60: SI | L60: MAYOR | M60: PRODUCCIÓN Y DIRECCIÓN TÉCNICA | N60: MARTIN DURANGO | Q60: ABIERTA | S60: ABIERTA | T60: SERVICIO AL CLIENTE | U60: ALEJANDRA CAMPOS ACOSTA | V60: N/R | W60: elizeth.castiblanco@clinicaunisabana.edu.co | X60: ADJUNTOS | Y60: NO
A61: 1 | B61: 57 | C61: 46083 | D61: MARZO | E61: CUNDINAMARCA | F61: FUNDACION ABOOD SHAIO | G61: FUND SHAIO | H61: DOSIS ANTICIPADA | I61: Buen día, Me permito informar acerca de la entrega inoportuna de la orden de magistrales-estériles y NPT del día 28/02/2026 de la Fundación Clínica Shaio. Los correos con las OP fueron enviados a las 12:04 y 11:48 AM, respectivamente. Según nuestro acuerdo de servicio la entrega debió realizarse máximo a las 17:00, no obstante, la entrega se realizó a las 18:20 poniendo en riesgo la oportunidad de entrega a los pacientes en los servicios. Además, por parte de producción no se realizo aviso a ninguno de los químicos farmacéuticos de la Fundación informando alguna novedad que retrasará la salida de las OP. Agradezco su atención, quedo atenta a respuesta con plan de mejora correspondiente. | J61: PRODUCTO NO CONFORME | K61: SI | L61: MAYOR | M61: PRODUCCIÓN Y DIRECCIÓN TÉCNICA | N61: MARTIN DURANGO | Q61: ABIERTA | S61: ABIERTA | T61: SERVICIO AL CLIENTE | U61: Yulieth Katerine Pedraza Amaya Quimico(a) Farmaceutico(a) | V61: PBX (601) 593 8210 | W61: yulieth.pedraza@shaio.org | X61: ADJUNTOS | Y61: NO
A62: 1 | B62: 58 | C62: 46083 | D62: MARZO | E62: CUNDINAMARCA | F62: HOSPITAL UNIVERSITARIO SAN IGNACIO | G62: HOSPITAL UNIVERSITARIO SAN IGNACIO | H62: DOSIS ANTICIPADA | I62: Cordial saludo Unidossis, El presente correo es para reportar las siguientes novedades/inconvenientes respecto a la entrega de la OP de Heparinas. Las DUs de Heparina debían llegar para el día (27/02/2026), sin embargo, a la fecha y hora (02/03/2026) no han llegado, informando desde unidossis que estaban apenas en proceso de despacho. Esto conlleva a la entrega NO oportuna de los medicamentos a los pacientes. Dicho lo anterior se solicita: Acciones de mejora a implementar para minimizar este tipo de inconvenientes, ya que afectan la atención y dispensación oportuna de los medicamentos. Reunión con el fin de esclarecer nuevamente los acuerdos de servicio, para que resulten favorables para ambas partes. Quedo atento a cualquier inquietud. Cordialmente, | J62: PRODUCTO NO CONFORME | K62: SI | L62: MAYOR | M62: PRODUCCIÓN Y DIRECCIÓN TÉCNICA | N62: MARTIN DURANGO | O62: 46094 | P62: 46094 | Q62: CERRADA | S62: ABIERTA | T62: SERVICIO AL CLIENTE | U62: Yuri Alberto Echeverri Pineda Químico Farmacéutico Asistencial | V62: Teléfono: (601) 5946161 Ext. 3007 | W62: yaecheverri@husi.org.co | X62: ADJUNTOS | Y62: NO
A63: 1 | B63: 59 | C63: 46083 | D63: MARZO | E63: OCCIDENTE | F63: FUNDACION CLINICA INFANTIL CLUB NOEL | G63: FUND CLINICA INFANTIL CLUB NOEL | H63: ONCOLOGÍA | I63: Por medio del presente me permito informar que, en el marco de las actividades rutinarias de control y seguimiento, durante la ejecución del inventario cíclico realizado en la fecha de ayer (22/01/2026), se evidenció un cruce de tres (3) viales correspondientes a dos medicamentos que actualmente se encuentran bajo su custodia, los cuales se relacionan a continuación: • Ifosfamida 1 g • Ifosfamida 2 g Dicha novedad fue identificada al momento de la verificación de los registros del sistema, motivo por el cual se procede a realizar el presente informe con el objetivo de dejar constancia formal del hallazgo, asegurar la trazabilidad del proceso, y dar cumplimiento a los lineamientos establecidos para el manejo, control y custodia de medicamentos. Es importante resaltar que este registro se efectúa como parte de las acciones preventivas y correctivas orientadas a mantener la integridad del inventario, garantizar la correcta gestión de los medicamentos y facilitar el análisis correspondiente para la toma de decisiones que se consideren necesarias. Quedo atenta a cualquier observación, aclaración, validación o instrucción adicional que estime pertinente respecto a este procedimiento, así como a las acciones que deban implementarse para su adecuada gestión y cierre | J63: PRODUCTO NO CONFORME | K63: SI | L63: MAYOR | M63: PRODUCCIÓN Y DIRECCIÓN TÉCNICA | N63: ANGELA MARCELA PARRA ESPITIA | Q63: ABIERTA | S63: ABIERTA | T63: SERVICIO AL CLIENTE | U63: Aura Janeth Mosquera H. Regente de Farmacia | V63: 602 485 44 04 Ext.: 1128 | W63: central.mezclas@fciclubnoel.com | X63: ADJUNTOS | Y63: NO
A64: 1 | B64: 60 | C64: 46083 | D64: MARZO | E64: CUNDINAMARCA | F64: HOSPITAL UNIVERSITARIO SAN IGNACIO | G64: HOSPITAL UNIVERSITARIO SAN IGNACIO | H64: ESTERILES | I64: Buenos días, se presenta novedad en la recepción técnica de 40 unidades de Solución de premediación (SSN 0,9% + KCl 10mEq + MgSO4 1g) Bolsa x 1000mL las cuales llegan en paquetes de a 5 unidades, estas bolsas deben llegar en empaque individual para conservar esterilidad hasta el momento de entrega a enfermería, re realizara devolución de 30 unidades para su reacondicionamiento, quedo atento anexo fotografías. Agradezco la atención prestada. Cordialmente; | J64: PRODUCTO NO CONFORME | K64: SI | L64: MAYOR | M64: PRODUCCIÓN Y DIRECCIÓN TÉCNICA | N64: MARTIN DURANGO | O64: 46094 | P64: 46094 | Q64: CERRADA | S64: ABIERTA | T64: SERVICIO AL CLIENTE | U64: Cesar Augusto Cortes Moncada Químico farmacéutico | V64: Teléfono: 5946161 ext. 4252 – 1410 - 3312 | W64: cacortes@husi.org.co | X64: ADJUNTOS | Y64: NO
A65: 1 | B65: 61 | C65: 46083 | D65: MARZO | E65: CUNDINAMARCA | F65: HOSPITAL UNIVERSITARIO SAN IGNACIO | G65: HOSPITAL UNIVERSITARIO SAN IGNACIO | H65: SOLIDOS | I65: Buenos días, cordila saludo El presente es para notificar error en proceso de reempaque por parte del tercero UNIDOSSIS en el código interno del medicamento se hace devolución de los mismos para su respectivo reproceso. Los medicamentos se requieren de forma prioritaria. Anexo tabla de los medicamentos y sus cantidades. | J65: ERROR EN ETIQUETA/CODIFICADO | K65: SI | L65: MAYOR | M65: PRODUCCIÓN Y DIRECCIÓN TÉCNICA | N65: DORIA NARVÁEZ REYES ENRIQUE | O65: 46094 | P65: 46094 | Q65: CERRADA | S65: ABIERTA | T65: SERVICIO AL CLIENTE | U65: Cesar Augusto Cortes Moncada Químico farmacéutico | V65: Teléfono: 5946161 ext. 4252 – 1410 - 3312 | W65: cacortes@husi.org.co | X65: ADJUNTOS | Y65: NO
A66: 1 | B66: 62 | C66: 46083 | D66: MARZO | E66: OCCIDENTE | F66: Clínica San Rafael de Popayán | G66: Clínica San Rafael de Popayán | H66: ESTERILES | I66: Se realiza reporte por calidad teniendo en cuenta que día de hoy se realizó la recepción de 2 preparaciones de Paclitaxel correspondiente a las pacientes Gloria Pacho y Lorenza Ulcue, evidenciando que las preparaciones cuentan con extensiones Cyto-set, en lugar de equipo fotoprotector como se solicitó el día de ayer. | J66: PRODUCTO NO CONFORME | K66: SI | L66: MAYOR | M66: PRODUCCIÓN Y DIRECCIÓN TÉCNICA | N66: ANGELA MARCELA PARRA ESPITIA | Q66: ABIERTA | S66: ABIERTA | T66: SERVICIO AL CLIENTE | U66: MARIA DEL MAR PERAFAN | V66: 602 835 3810 | W66: serviciofarmaceutico.cirugiacsrp@stewardcolombia.org | X66: ADJUNTOS | Y66: NO
A67: 1 | B67: 63 | C67: 46085 | D67: MARZO | E67: MARLY CUNDINAMARCA | F67: CLINICA DE MARLY S.A. | G67: CLINICA DE MARLY BOGOTA | H67: SOLIDOS | I67: "El pasado 28/01/2026 se recibe los medicamento de reempaque de una orden de tableteria por parte de la sede Puente Aranda, la cual presenta retrasos en su entrega y un error en la etiqueta para el medicamento MONTELUKAST 5 MG TABLETA MASTICABLE con el código 82275. Este error consta de la presentacion del medicamento en donde todas las 30 unidades indican dosis de 25 mg, pero en el despacho entregado por parte de Unidossis indica que la presentación es correcta 5 mg. Cabe aclarar que la ORDEN DE DESPACHO es 0208O, para el medicamento en reempaque entregado. Por favor revisar el caso. " | J67: ERROR EN ETIQUETA/CODIFICADO | K67: SI | L67: MAYOR | M67: PRODUCCIÓN Y DIRECCIÓN TÉCNICA | N67: RUBER VALECILLOS | Q67: ABIERTA | S67: ABIERTA | T67: SERVICIO AL CLIENTE | U67: DANIELA GASCA - QUÍMICA FARMACÉUTICA | V67: 3436600 EXT 2502 | W67: esteriles.farmacia@clinicademarly.com.co | X67: ADJUNTOS | Y67: NO
A68: 1 | B68: 64 | C68: 46085 | D68: MARZO | E68: CUNDINAMARCA | F68: FUNDACION ABOOD SHAIO | G68: FUND SHAIO | H68: TODAS | I68: Buenas tardes. Por medio del presente correo queremos notificar el incumplimiento del acuerdo de servicio en relación con la hora de entrega, así como la falta de comunicación clara y oportuna respecto a la entrega de las unidosis y nutriciones parenterales correspondientes al día 03-03-2026. Inicialmente, desde el área de interpretación se nos informó que se presentaba un inconveniente con la OP de estériles (unidosis), por lo cual se realizaría un primer envío con las nutriciones y los magistrales. Considerando que la OP de estériles representa la menor proporción frente al total de la OP de magistrales, nutriciones y estériles, se autorizó la entrega parcial con el fin de no afectar la mayoría de las pacientes. Esta comunicación se recibió aproximadamente a las 3:50 p.m. Posteriormente se realiza un plan de contingencia con el personal asistencial de los servicios que requerían las unidosis de la OP estériles, esta situación ocasiona reprocesos internos, ya que, con el propósito de garantizar la administración oportuna de las dosis a los pacientes, el servicio farmacéutico de la clínica debe comunicarse de manera inmediata con las áreas de cuidados intensivos y hospitalización para sincronizar los tiempos de atención. Posteriormente, hacia las 5:30 p.m., nos comunicamos nuevamente para verificar el estado del envío, momento en el cual se nos informó que no se había realizado la entrega parcial. En consecuencia, el despacho fue aplazado hasta la finalización de la OP de unidosis estériles, lo que generó un retraso adicional. Adicionalmente, el plan de contingencia mencionado anteriormente no fue efectivo por el no envío del despacho parcial. Finalmente, la OP llegó sobre las 06:15 PM, incumpliendo el acuerdo de servicio (adjunto correo en que se notifica el incumplimiento del acuerdo de servicio del día 28-02-2026, sin respuesta alguna). Por otro lado en horas de la mañana se presento la novedad en que no se entregaron las 300 heparinas que se habrían solicitado en modo maquila (solo llegaron 100 unidades); junto con las nutriciones llegó el restante, generando otro reporoceso, ya que para ello se tienen horarios destinados en la entrega de la maquila. Adicionalmente, en horas de la tarde mandaron las remisiones (remisiones que no se habían enviado en horas de la mañana por problemas en el sistema de ustedes) y se relacionaron de forma incorrecta las cantidades de heparina y la remisión de morfina no llegó. Agradecemos se revisen los hechos ocurridos y se tomen las medidas necesarias para evitar que situaciones similares se presenten nuevamente, además de tener claridad en la información que se maneja y una respuesta a esta queja, ya que se han presentado quejas sin respuesta o solución alguna. | J68: ENTREGA FUERA DEL ACUERDO DE SERVICIO | K68: SI | L68: MAYOR | M68: PRODUCCIÓN Y DIRECCIÓN TÉCNICA | N68: MARTIN DURANGO | Q68: ABIERTA | S68: ABIERTA | T68: SERVICIO AL CLIENTE | U68: Oscar Alfonso Vargas Bautista Químico(a) Farmacéutico(a) | V68: (601) 593 8210 | W68: alfonso.vargas@shaio.org | X68: ADJUNTOS | Y68: NO
A69: 1 | B69: 65 | C69: 46085 | D69: MARZO | E69: CUNDINAMARCA | F69: HOSPITAL UNIVERSITARIO SAN IGNACIO | G69: HOSPITAL UNIVERSITARIO SAN IGNACIO | H69: TODAS | I69: Buenos días equipo Unidossis, reciban un cordial saludo, Por medio del presente correo, solicito amablemente a colaboración con el envío e las respuestas de las PQRS que se encuentran abiertas a la fecha y que corresponden a casos reportados en el 2025:  FECHA RESPONSABLE DESCRIPCION 14/10/2025 YURI ECHEVERRI DU Heparia con pivote roto 7/12/2025 ERIKA ROMERO Du piperacilina con las etiquetas cruzadas, no corresponde el volumen de la jeringa con el declarado en la etiqueta 15/12/2025 YURI ECHEVERRI OP de 50 DU de succinilcolina, llegan 49 26/12/2025 YURI ECHEVERRI OP de 50 DU de succinilcolina, programada para entrega el 24/12/2025, llega el 25/12/2025 y solo llegan 49 unidades Por favor enviar la información lo más pronto posible ya que debemos enviar el informe de gestión de la central de mezclas del 2025 a la dirección general del hospital y es lo único que tenemos pendiente. | J69: INCUMPLIMIENTO ACTIVIDADES O COMPROMISOS | K69: SI | L69: MAYOR | M69: PRODUCCIÓN Y DIRECCIÓN TÉCNICA | N69: DIANA M MUÑOZ M | Q69: CERRADA | S69: ABIERTA | T69: SERVICIO AL CLIENTE | U69: Claudia Tinoco Rairán Química Farmacéutica de Aseguramiento de la Calidad | V69: Teléfono: 57 (1) 5946161 Ext. 1066 | W69: cytinoco@husi.org.co | X69: ADJUNTOS | Y69: NO
A70: 1 | B70: 66 | C70: 46086 | D70: MARZO | E70: OCCIDENTE | F70: STEWARD DE COLOMBIA | G70: Clínica San Rafael de Popayán | H70: ONCOLOGÍA | I70: Cordial saludo El presente correo es para realizar el reporte de la presencia de burbujas en las preparaciones oncológicas, específicamente para las preparaciones de Paclitaxel que vienen en frasco, esta eventualidad genera problemas al momento de pasar el medicamento por el equipo bomba, ya que no permite la administración del mismo. Solicito amablemente de su colaboración con la verificación del caso, con la finalidad de validar si es posible realizar un plan de mejora por parte de la central de mezclas para evitar la reincidencia de este tipo de situaciones. | J70: PRODUCTO NO CONFORME | K70: SI | L70: MAYOR | M70: PRODUCCIÓN Y DIRECCIÓN TÉCNICA | N70: ANGELA MARCELA PARRA ESPITIA | Q70: ABIERTA | S70: ABIERTA | T70: SERVICIO AL CLIENTE | U70: MARIA DEL MAR PERAFAN | V70: 602 8353810 | W70: serviciofarmaceutico.cirugiacsrp@stewardcolombia.org | X70: ADJUNTOS | Y70: NO
A71: 1 | B71: 67 | C71: 46086 | D71: MARZO | E71: CUNDINAMARCA | F71: HOSPITAL UNIVERSITARIO SAN IGNACIO | G71: HOSPITAL UNIVERSITARIO SAN IGNACIO | H71: TODAS | I71: Cordial saludo El presente con el fin de reportar queja en cuanto al retraso en entrega de las dosis unitarias de estériles del día 4 de marzo las cuales se recibieron a las 18:15 (horario pactado 17:00). Adjunto envío documento. Quedo atenta a cualquier inquietud. | J71: ENTREGA FUERA DEL ACUERDO DE SERVICIO | K71: SI | L71: MAYOR | M71: PRODUCCIÓN Y DIRECCIÓN TÉCNICA | N71: LEIDY MAYURY TORRES TRUJILLO | Q71: ABIERTA | S71: ABIERTA | T71: SERVICIO AL CLIENTE | U71: Luisa Ovalle Químico Farmacéutico Asistencial | V71: Teléfono: (601) 5946161 Ext. 3007 | W71: luovalle@husi.org.co | X71: ADJUNTOS | Y71: NO
A72: 1 | B72: 68 | C72: 46086 | D72: MARZO | E72: CUNDINAMARCA | F72: HOSPITAL SIMON BOLIVAR SUBRED NORTE | G72: HOSPITAL SIMON BOLIVAR | H72: TODAS | I72: A quien corresponda, Por medio de la presente deseo presentar una queja formal respecto al retraso en la entrega de las dosis anticipadas del medicamento HEPARINA 3000 UI - 475 unidades que se solicitaron con la debida anticipación (24 FEBRERO 2026) para el Hospital Simón Bolívar. Según lo acordado, estas dosis debían ser entregadas en la fecha establecida (Máximo 48 h después de la solicitud, 27 Febrero 2026); sin embargo, hasta el momento no se ha cumplido con dicha entrega completa, entregan 175 unidades el día 3/3/2026 y no se ha brindado una explicación clara sobre el motivo del retraso. Esta situación está generando inconvenientes en la continuidad del tratamiento y en la correcta planificación del suministro de medicamentos. Adicionalmente, las unidades llegadas a nuestro servicio farmacéutico datan con fecha de preparación del 1/3/2026, lo cual indica que tardan 48 horas en despachar después de preparadas, lo que disminuye la vida útil dentro del servicio, intensificando la posible pérdida por fecha de vencimiento. Solicito respetuosamente que se revise con urgencia este caso, se informe el estado actual de la entrega y se adopten las medidas necesarias para evitar que este tipo de situaciones se repitan en el futuro. | J72: ENTREGA FUERA DEL ACUERDO DE SERVICIO | K72: SI | L72: MAYOR | M72: PRODUCCIÓN Y DIRECCIÓN TÉCNICA | N72: LEIDY MAYURY TORRES TRUJILLO | Q72: ABIERTA | S72: ABIERTA | T72: SERVICIO AL CLIENTE | U72: QUIMICO FARMACEUTICO ASISTENCIAL | V72: N/R | W72: qfasistencialsimon@gmail.com | X72: ADJUNTOS | Y72: NO
A73: 1 | B73: 69 | C73: 46087 | D73: MARZO | E73: ANTIOQUIA | F73: HOSPITAL ALMA MATER | G73: HOSPITAL ALMA MATER | H73: NPT | I73: Buenos días, espero que se encuentre muy bien. Por medio de la presente me permito realizar un reporte de tecnovigilancia relacionado con el dispositivo médico BOLSA EVA NUTRICION PARENTERAL 3000 ML, lote 580335H21. Al instalar la nutrición parenteral, se observa una fuga constante por una de las vías, la cual se encontraba cerrada a nivel de la pinza azul. Se realizan intentos para corregir la fuga; sin embargo, no es posible debido a que la pérdida es abundante. En consecuencia, se procede al retiro de la nutrición, generando una afectación en el paciente. Ante esta situación, se realiza el presente reporte con el fin de contribuir a las acciones de mejora correspondientes y se solicita la reposición del dispositivo. Muchas gracias por su apoyo. | J73: PRODUCTO NO CONFORME | K73: SI | L73: MAYOR | M73: PRODUCCIÓN Y DIRECCIÓN TÉCNICA | N73: CARMONA RIOS FRANCISCO JULIAN | Q73: ABIERTA | S73: ABIERTA | T73: SERVICIO AL CLIENTE | U73: VALENTINA RODRIGUIEZ QUIMICO FARMACEUTICO | V73: N/R | W73: valentina.rodriguezr@almamater.hospital | X73: ADJUNTOS | Y73: NO
A74: 1 | B74: 70 | C74: 46087 | D74: MARZO | E74: CUNDINAMARCA | F74: CLINICA UNIVERSIDAD DE LA SABANA | G74: CLINICA UNIVERSITARIA DE LA SABANA | H74: SOLIDOS | I74: Señores UNIDOSSIS SAS notificaciones@unidossis.com.co Asunto: Notificación formal de desviación de calidad – Medicamento de control especial Metadona 10 mg, lote 250502-09. Cordial saludo, Por medio de la presente, y en ejercicio de las funciones de seguimiento y control de los procesos asociados al manejo de medicamentos de control especial, nos permitimos informar una desviación de calidad evidenciada durante las actividades de alistamiento y dispensación del medicamento Metadona 10 mg, correspondiente al lote 250502-09, con fecha de vencimiento 05/2027. De acuerdo con la revisión de la trazabilidad del proceso, se verificaron las recepciones técnicas del empaque primario desde el momento de su ingreso al Servicio Farmacéutico el día 10 de noviembre de 2025. En dicha oportunidad, las unidades fueron revisadas individualmente tanto por el auxiliar de farmacia como por el regente de farmacia, dejando constancia de conformidad respecto a la cantidad recibida y las condiciones físicas del producto. Posteriormente, el medicamento fue remitido al área de adecuación con su correspondiente orden de producción el día 15 de noviembre de 2025, donde se efectuó nuevamente la verificación física de las unidades y la validación de la información requerida para el proceso de reempaque. Así mismo, el día 28 de noviembre de 2025 se recibió el medicamento debidamente sellado. No obstante lo anterior, y como resultado de la rotación del inventario, el día 11 de febrero de 2026, al momento de realizar el alistamiento de medicamentos de control especial para su entrega al personal del turno, se evidenció que una de las unidades se encontraba completamente sellada, sin signos aparentes de manipulación ni fuga, pero sin contener la tableta en su interior. Teniendo en cuenta que se trata de un medicamento sometido a control especial, la situación descrita constituye una desviación relevante dentro de los procesos de aseguramiento de calidad y control, por lo cual resulta necesario adelantar el análisis técnico correspondiente que permita determinar las causas del evento reportado | J74: PRODUCTO NO CONFORME | K74: SI | L74: MAYOR | M74: PRODUCCIÓN Y DIRECCIÓN TÉCNICA | N74: DORIA NARVÁEZ REYES ENRIQUE | Q74: ABIERTA | S74: ABIERTA | T74: SERVICIO AL CLIENTE | U74: GIOVANNI VALENCIA PINZÓN Subdirector Administrativo y Logístico. Clínica Universidad de La Saban | V74: 8617777 | W74: contratos@clinicaunisabana.edu.co | X74: ADJUNTOS | Y74: NO
A75: 1 | B75: 71 | C75: 46090 | D75: MARZO | E75: CUNDINAMARCA | F75: SOCIEDAD DE CIRUGIA DE BOGOTA HOSPITAL DE SAN JOSE | G75: HOSPITAL DE SAN JOSE | H75: ESTERILES | I75: "Buenos dias. Con el presente documento quiero notificar que para el día 09/03/2026 se ha recibido MENOS DE LA MITAD de Hidromorfona JP de la orden de producción enviada desde el martes 04/03/2026 no se brindo información oportuna sobre el retraso ni se respondió a las inquietudes expresadas, la inoportunidad de entrega genera dificultades para el cubrimiento de las necesidades de la IPS aumento el riesgo de acontecimiento de sucesos de seguridad, Esta situación también genera dificultades para la generación de la orden de producción de la semana del producto mencionado al cruzarse los requerimientos, la situación ha sido repetitiva y se ha presentado con todos los productos a adecuar en dosis estándar, Dado lo anterior, se le solicita atentamente a Unidossis que se cumpla con los tiempos estipulados para no generar traumatismos en la operación de la IPS. " "Buenos dias. Con el presente documento quiero notificar que para los días 07 y 08/03/2026 se presentaron retrasos en la hora de llegada de las nutriciones parenterales y anrtibióticos, ya que de acuerdo con el contrato de servicios estas preparaciones deben entregarse al hospital como máximo 17:30 y se ha superado dicha hora, (llegada a las 20:00 y 16:30), esto ha generado gran molestia en los servicios puesto que la llegada tardía de las nutriciones ocasiona que la entrega interna en el hospital se retrase, adicionalmente no se garantiza soporte nutricional ni cubrimiento de requerimiento calórico a pacientes con necesidades especiales y se generan variaciones en los horarios de administración de antibióticos en pediatría auemntando el riesgo de fallos terapéuticos. Se realizó el seguimiento al envío oportuno de las ordenes evidenciando que se cumple con el envío antes de las 13:00, se recibió notificación de recibido y no se notificó de inconvenientes de transporte. Se realiza llamada telefónica en donde informan un aumento en el volumen de pedidos pero esta información sólo es aportada después del incumplimiento, es necesario revisar el proceso y de ser necesario ajustar los horarios para evitar los riesgos asociados al inicio atemporal de las nutriciones y adecuaciones. Dado lo anterior, se le solicita atentamente a Unidossis que se cumpla con los tiempos estipulados según el acuerdo contractual descrito en el anexo técnico operativo para no generar traumatismos en la operación de la IPS o que se realicen ajuste al proceso. " | J75: ENTREGA FUERA DEL ACUERDO DE SERVICIO | K75: SI | L75: MAYOR | M75: PRODUCCIÓN Y DIRECCIÓN TÉCNICA | N75: KATY KARINA ORTEGA ACEVEDO | Q75: ABIERTA | S75: ABIERTA | T75: SERVICIO AL CLIENTE | U75: María Saavedra Químico Farmacéutico | V75: 3538000 Ext. 468-422 | W75: rordenespro20211123@gmail.com | X75: ADJUNTOS | Y75: NO
A76: 1 | B76: 72 | C76: 46090 | D76: MARZO | E76: CUNDINAMARCA | F76: HOSPITAL UNIVERSITARIO SAN IGNACIO | G76: HOSPITAL UNIVERSITARIO SAN IGNACIO | H76: NPT | I76: Cordial Saludo Unidossis, El presente es para reportar novedad con la hora de entrega de NPT Adulto: Fecha de la novedad: 07/03/2026 El día 07/03/2026 se envió solicitud de 6 preparaciones de NPT a las 11:13, sin embargo, estas llegaron a las 18:30 al hospital. Solicitamos amablemente su colaboración indicando lo ocurrido, puesto que, por protocolos del HUSI estas preparaciones deben estar disponibles para el paciente antes de las 18:00 para dar cumplimiento al tratamiento. Envía adjunto documento de registro Dicho esto se solicita: Implementar acciones de mejora que permitan minimizar este tipo de inconvenientes, mejorando así la oportunidad en los tiempos de entrega de las preparaciones. Cordial saludo El presente con el fin de reportar queja en cuanto al retraso en entrega de las dosis unitarias de estériles del día 7 de marzo las cuales se recibieron a las 18:30 (horario pactado 17:00). Adjunto envío documento. Quedo atenta a cualquier inquietud. | J76: ENTREGA FUERA DEL ACUERDO DE SERVICIO | K76: SI | L76: MAYOR | M76: PRODUCCIÓN Y DIRECCIÓN TÉCNICA | N76: LEIDY MAYURY TORRES TRUJILLO | Q76: ABIERTA | S76: ABIERTA | T76: SERVICIO AL CLIENTE | U76: Jenny Paola Angarita Gil Química Farmacéutica Asistencial | V76: Teléfono: (601) 5946161 Ext. 3007 | W76: jpangarita@husi.org.co | X76: ADJUNTOS | Y76: NO
A77: 1 | B77: 73 | C77: 46090 | D77: MARZO | E77: OCCIDENTE | F77: ATENCION INTEGRAL EN CASA | G77: ATENCION INTEGRAL EN CASA | H77: NPT | I77: Reciban un cordial saludo Reporto queja por el envío del producto de alimentación del paciente del asunto, el cual ha presentado constantemente retrasos importantes en la entrega, y en otras oportunidades dejando el paciente sin alimentación (3 de febrero). La falta de oportunidad en la entrega del producto ha dificultado los tiempos de administración y ha impactado en la logística interna del personal de salud y administrativo que atiende el paciente en domicilio. Este incumplimiento ha favorecido en parte las hospitalizaciones del paciente por descompensación de su medio interno. Igualmente el destino donde se debería trasladar la alimentación queda a 15 minutos de palmira. Solicito su especial apoyo para solucionar de fondo las dificultades presentadas con el transporte la cual no ha generado incremento en los costos operativos y en la seguridad de nuestro paciente. Quedo atento, mil gracias | J77: ENTREGA FUERA DEL ACUERDO DE SERVICIO | K77: SI | L77: MAYOR | M77: PRODUCCIÓN Y DIRECCIÓN TÉCNICA | N77: ANGELA MARCELA PARRA ESPITIA | Q77: ABIERTA | S77: ABIERTA | T77: SERVICIO AL CLIENTE | U77: Carlos Emilio Rangel Hernandez Auditoría | V77: PBX: 6016651379 Ext 908 | W77: auditoria@atencionintegralencasa.com.co | X77: ADJUNTOS | Y77: NO
A78: 1 | B78: 74 | C78: 46091 | D78: MARZO | E78: OCCIDENTE | F78: CHRISTUS SINERGIA | G78: FARALLONES | H78: ESTERILES | I78: Buen día: La presente es para reportar un nuevo error de etiquetado y de preparación correspondiente a la unidosis solicitada el día 10/03/2026 para el paciente Jose Francisco Muñoz. Según la orden de producción enviada, el medicamento debía ser preparado a una concentración de 30 mg/mL para una dosis total de 1500 mg, lo que corresponde a un volumen final de 50 mL. No obstante, al momento de recibir el diluido se evidenció que la preparación estaba claramente realizada en un volumen aproximado de 100 mL. Esto se pudo verificar debido a que la solución salina utilizada correspondía a una presentación de este volumen y, adicionalmente, mediante verificación por peso se evidenció que el contenido era superior a 50 mL. A pesar de lo anterior, la etiqueta del preparado indicaba que el volumen final correspondía a 50 mL. Adjunto evidencias correspondientes: Con este evento se completa la segunda novedad presentada con el servicio en tan solo una semana desde el inicio de operaciones. Hasta el momento no hemos recibido una respuesta de fondo frente a las situaciones previamente reportadas. Agradecemos realizar la revisión correspondiente, identificar la causa de estos eventos y remitir las acciones correctivas y preventivas que se implementarán para evitar que este tipo de situaciones se repitan. Quedamos atentos a su respuesta. | J78: ERROR EN ETIQUETA/CODIFICADO | K78: SI | L78: MAYOR | M78: PRODUCCIÓN Y DIRECCIÓN TÉCNICA | N78: ANGELA MARCELA PARRA ESPITIA | Q78: ABIERTA | S78: ABIERTA | T78: SERVICIO AL CLIENTE | U78: LAURA MARCELA RODRIGUEZ | V78: N/R | W78: laura.rodriguez@christus.co | X78: ADJUNTOS | Y78: NO
A79: 1 | B79: 75 | C79: 46091 | D79: MARZO | E79: CUNDINAMARCA | F79: HOSPITAL UNIVERSITARIO SAN IGNACIO | G79: HOSPITAL UNIVERSITARIO SAN IGNACIO | H79: TODAS | I79: Buenos días equipo Unidossis, reciban un cordial saludo, Por medio del presente, me permito enviar el consolidado de las PQRS que se han enviado en lo que va del 2026, solicito amablemente la colaboración con el envío de las respuestas a las revisiones de estos casos:  FECHA PQRS Cantidad 6/1/2026 Faltante de 1 amp bicarbonato, el 25/12/2025 se debían gastar 12 viales para la preparación de 60 DUs, el día 26/12/2025 se identifica la salida de 1 unidad 1 23/1/2026 Las DUs de Heparina debían llegar para el día (20/01/2026), sin embargo, llegaron hasta el día (22/01/2026) en horas de la tarde. Esto conlleva a la entrega NO oportuna de los medicamentos a los pacientes. 165 26/1/2026 Llegada tarde DU antibióticos 18:39 el 23/01/2026 26 26/1/2026 Se informo desde Unidossis que las DUs tenían un ligero retraso y que llegaban en horas de la tarde del viernes (23/01/2026), 50 bicarbonato, heparina 325, propofol 56 431 22/1/2026 Se encontraron unidades de a. ursodesoxicolico identificadas como bisoprolol 43 28/1/2026 Llegada tarde de du estériles a las 18:27 10 12/2/2026 Retraso de entrega de DU estériles del 10 de febrero a las 18:25 10 2/3/2026 Se recibieron 40 mezclas de hidratación sin empaque, las bolsas venian en una bolsa grande con 5 unidades cuando el empaque debe ser individual 40 2/3/2026 DU anticipadas de bicarbonato, heparina y propofol que debían llegar el 27/02/2026 y a la fencah no han llegado 93 2/3/2026 Se encontró que la op de 18730 unidades de reempaque, todas las unidades tenían el código interno del HUSI errado 18730 | J79: INCUMPLIMIENTO ACTIVIDADES O COMPROMISOS | K79: SI | L79: MAYOR | M79: PRODUCCIÓN Y DIRECCIÓN TÉCNICA | N79: DIANA M MUÑOZ M | Q79: ABIERTA | S79: ABIERTA | T79: SERVICIO AL CLIENTE | U79: Claudia Tinoco RairánQuímica Farmacéutica de Aseguramiento de la Calidad | V79: Teléfono: 57 (1) 5946161 Ext. 1066 | W79: cytinoco@husi.org.co | X79: ADJUNTOS | Y79: NO
A80: 1 | B80: 76 | C80: 46093 | D80: MARZO | E80: CUNDINAMARCA | F80: CLINICA UNIVERSIDAD DE LA SABANA | G80: CLINICA UNIVERSITARIA DE LA SABANA | H80: SOLIDOS | I80: Buenos días. Cordial saludo, Por medio del presente, envío reclamo técnico de calidad , debido a que, durante el proceso de recepción / dispensación, se evidenció que un empaque secundario de la tableta clonidina 150mcg se encontraba sin el medicamento en su interior. Al momento de la verificación, el empaque secundario se encontraba cerrado y en condiciones físicas aparentemente normales; no obstante, al proceder con su apertura se evidenció la ausencia del medicamento en su interior. Quedo atenta a la reposición del producto, la emisión de la respectiva nota crédito y el envío del plan de acción correspondiente. Quedo atenta a sus comentarios. | J80: ERROR DE RE EMPAQUE | K80: SI | L80: MAYOR | M80: PRODUCCIÓN Y DIRECCIÓN TÉCNICA | N80: DORIA NARVÁEZ REYES ENRIQUE | Q80: ABIERTA | S80: ABIERTA | T80: SERVICIO AL CLIENTE | U80: CLAUDIA PATRICIA RAMOS | V80: 8617777 | W80: claudia.ramos2@clinicaunisabana.edu.co | X80: ADJUNTOS | Y80: NO
A81: 1 | B81: 77 | C81: 46093 | D81: MARZO | E81: OCCIDENTE | F81: CHRISTUS SINERGIA | G81: FARALLONES | H81: ESTERILES | I81: Buenas tardes, cordial saludo De manera respetuosa informo la siguiente novedad identificada durante la recepción de preparaciones magistrales provenientes de la central de mezclas tercerizada: El día sábado, al momento de la verificación de las preparaciones recibidas, se evidenció un cruce de etiquetas entre dos preparaciones antibióticas correspondientes a diferentes pacientes, lo cual representa un riesgo potencial para la seguridad del paciente y genera impacto en los costos institucionales debido a la necesidad de reprocesar o reemplazar las preparaciones. Los casos identificados son los siguientes: Paciente: JOSE DAMARIO JIMENEZ Medicamento solicitado en orden de producción: Piperacilina + Sulbactam Medicamento recibido: Ampicilina + Sulbactam Paciente: JOSE FRANCISCO MUÑOZ LOPEZ Medicamento solicitado en orden de producción: Ampicilina + Sulbactam Medicamento recibido: Piperacilina + Sulbactam Adjunto evidencia fotográfica y OP | J81: ERROR DE RE EMPAQUE | K81: SI | L81: MAYOR | M81: PRODUCCIÓN Y DIRECCIÓN TÉCNICA | N81: ANGELA MARCELA PARRA ESPITIA | Q81: ABIERTA | S81: ABIERTA | T81: SERVICIO AL CLIENTE | U81: EILIN PATRICIA BOHORUEZ QUIMICA FARMACEUTICA | V81: N/R | W81: eilin.bohorquez@christus.co | X81: ADJUNTOS | Y81: NO
A82: 1 | B82: 78 | C82: 46094 | D82: MARZO | E82: CUNDINAMARCA | F82: HOSPITAL UNIVERSITARIO SAN IGNACIO | G82: HOSPITAL UNIVERSITARIO SAN IGNACIO | H82: ESTERILES | I82: Cordial saludo El presente con el fin de reportar queja en cuanto al retraso en entrega de las dosis unitarias de estériles del día 11 de marzo las cuales se recibieron a las 19:53 (horario pactado 17:00). Adjunto envío documento. Quedo atenta a cualquier inquietud. Cordialmente | J82: ENTREGA FUERA DEL ACUERDO DE SERVICIO | K82: SI | L82: MAYOR | M82: PRODUCCIÓN Y DIRECCIÓN TÉCNICA | N82: MARTIN DURANGO | Q82: ABIERTA | S82: ABIERTA | T82: SERVICIO AL CLIENTE | U82: Luisa Ovalle Químico Farmacéutico Asistencial | V82: Teléfono: (601) 5946161 Ext. 3007 | W82: luovalle@husi.org.co | X82: ADJUNTOS | Y82: NO
A83: 1 | B83: 79 | C83: 46094 | D83: MARZO | E83: MARLY CUNDINAMARCA | F83: VANTIVE S.A.S. | G83: VANTIVE | H83: DOSIS ANTICIPADA | I83: Buen día a todos. Francisco como te comenté el día de ayer, las heparinas jeringas prellenadas que llegaron a las clínicas renales, llegaron con información incorrecta en la etiqueta en lo relacionado a sus condiciones de almacenamiento por tal motivo con el fin de evitar tener que realizar devolución del producto de todas las unidades renales, agradezco el día de hoy me envíen carta aclaratoria sobre las condiciones correctas de almacenamiento y haciendo claridad que no requieren un empaque que proteja de la luz, para así mismo socializar con las clínicas renales y evitar el reproceso de devolución para re- etiquetado. Inclusive en la ficha técnica también aparece el error de almacenamiento. | J83: ERROR EN ETIQUETA/CODIFICADO | K83: SI | L83: MAYOR | M83: PRODUCCIÓN Y DIRECCIÓN TÉCNICA | N83: RUBER VALECILLOS | Q83: ABIERTA | S83: ABIERTA | T83: SERVICIO AL CLIENTE | U83: 0 | V83: 0 | W83: 0 | X83: ADJUNTOS | Y83: NO
A84: 1 | B84: 80 | C84: 46094 | D84: MARZO | E84: CUNDINAMARCA | F84: HOSPITAL UNIVERSITARIO SAN IGNACIO | G84: HOSPITAL UNIVERSITARIO SAN IGNACIO | H84: ESTERILES | I84: Cordial saludo El presente con el fin de reportar queja en cuanto al retraso en entrega de las dosis unitarias de estériles del día 12 de marzo las cuales se recibieron a las 18:23 (horario pactado 17:00). Adjunto envío documento. Quedo atenta a cualquier inquietud. | J84: ENTREGA FUERA DEL ACUERDO DE SERVICIO | K84: SI | L84: MAYOR | M84: PRODUCCIÓN Y DIRECCIÓN TÉCNICA | N84: MARTIN DURANGO | Q84: ABIERTA | S84: ABIERTA | T84: SERVICIO AL CLIENTE | U84: Luisa Ovalle Químico Farmacéutico Asistencial | V84: Teléfono: (601) 5946161 Ext. 3007 | W84: luovalle@husi.org.co | X84: ADJUNTOS | Y84: NO
A85: 1 | B85: 81 | C85: 46097 | D85: MARZO | E85: OCCIDENTE | F85: CHRISTUS SINERGIA | G85: PALMA REAL | H85: ESTERILES | I85: Espero se encuentren muy bien. Me permito remitir formato de PQR adjunto, relacionado con los tiempos de entrega de las producciones correspondientes a los días viernes 13 y sábado 14 de marzo del 2026, para su conocimiento, revisión y gestión correspondiente. Agradecemos su apoyo en la verificación de la situación descrita y en la implementación de las acciones que permitan garantizar el cumplimiento de los tiempos de entrega establecidos. Quedamos atentos a sus comentarios y a la información que consideren pertinente frente al caso. Cordialmente, | J85: ENTREGA FUERA DEL ACUERDO DE SERVICIO | K85: SI | L85: MAYOR | M85: PRODUCCIÓN Y DIRECCIÓN TÉCNICA | N85: ANGELA MARCELA PARRA ESPITIA | Q85: ABIERTA | S85: ABIERTA | T85: SERVICIO AL CLIENTE | U85: ANDREA KATERINE CAICEDO DIAS | V85: N/R | W85: quimicofarmaceutico1.cpr@christus.co | X85: ADJUNTOS | Y85: NO
A86: 1 | B86: 82 | C86: 46097 | D86: MARZO | E86: OCCIDENTE | F86: CHRISTUS SINERGIA | G86: PALMA REAL | H86: ESTERILES | I86: El día 17 de octubre fueron enviadas a sus instalaciones 50 unidades de Fentanilo 250 mcg/5 mL (Blaskov). Posteriormente, debido a que no se contaba con información sobre la estabilidad del medicamento en sus bases de datos, se realizó la consulta directamente con el laboratorio fabricante, quien informó que el producto presenta baja estabilidad, motivo por el cual se solicitó la devolución de las ampollas. Al momento de recibir el producto, se evidenció un faltante de 5 ampollas. Tras realizar la consulta correspondiente, se nos informó que 3 de estas unidades no habían sido localizadas. Teniendo en cuenta lo anterior solicitamos de manera atenta la devolución a la mayor brevedad posible de las unidades faltantes. En caso de confirmarse la pérdida de dichas ampollas, agradecemos remitir los soportes del reporte realizado ante los entes de control correspondientes, así como la documentación relacionada con el proceso administrativo y legal que esta situación implica, teniendo en cuenta que se trata de un medicamento de control especial bajo su custodia contractual. | J86: DIFERENCIA EN INVENTARIO EN CUSTODIA | K86: SI | L86: MAYOR | M86: PRODUCCIÓN Y DIRECCIÓN TÉCNICA | N86: ANGELA MARCELA PARRA ESPITIA | Q86: ABIERTA | S86: ABIERTA | T86: SERVICIO AL CLIENTE | U86: ANDREA KATERINE CAICEDO DIAS | V86: N/R | W86: quimicofarmaceutico1.cpr@christus.co | X86: ADJUNTOS | Y86: NO
A87: 1 | B87: 83 | C87: 46097 | D87: MARZO | E87: CUNDINAMARCA | F87: HOSPITAL UNIVERSITARIO SAN IGNACIO | G87: HOSPITAL UNIVERSITARIO SAN IGNACIO | H87: ESTERILES | I87: Cordial saludo El presente con el fin de reportar queja en cuanto al retraso en entrega de las dosis unitarias de estériles del día 14 de marzo (hora de envío OP 12:23) y fueron recibidas a las 19:26 (horario pactado 17:00). Adjunto envío documento. Agradezco la atención prestada al presente y quedo atenta. | J87: ENTREGA FUERA DEL ACUERDO DE SERVICIO | K87: SI | L87: MAYOR | M87: PRODUCCIÓN Y DIRECCIÓN TÉCNICA | N87: MARTIN DURANGO | Q87: ABIERTA | S87: ABIERTA | T87: SERVICIO AL CLIENTE | U87: Luisa Ovalle Químico Farmacéutico Asistencial | V87: Teléfono: (601) 5946161 Ext. 3007 | W87: luovalle@husi.org.co | X87: ADJUNTOS | Y87: NO
A88: 1 | B88: 84 | C88: 46097 | D88: MARZO | E88: EJE CAFETERO | F88: HOSPITAL UNIVERSITARIO SAN JORGE PEREIRA | G88: HOSPITAL UNIVERSITARIO SAN JORGE DE PEREIRA | H88: ESTERILES | I88: Buenos días, Por medio del presente informo que se identificó un error en la estabilidad registrada en las etiquetas de las mezclas oncológicas del paciente JOSTIN ALEJANDRO MOSQUERA, correspondiente a las preparaciones realizadas el viernes 13 y lunes 16 de marzo de 2026. En dichas etiquetas se indica una estabilidad de 6 horas para la Citarabina 500 mg solución inyectable , cuando la estabilidad correcta para estas preparaciones corresponde a 24 horas. Esta situación representa un problema dentro del proceso, ya que puede afectar la programación, dispensación y manejo adecuado de las mezclas oncológicas, generando reprocesos y posibles inconsistencias en la información utilizada por el equipo. Adjunto a este correo las fotografías como evidencia del error identificado. Agradezco realizar la revisión correspondiente y solicito amablemente establecer un plan de mejora que permita prevenir que este tipo de situaciones vuelva a presentarse. Quedo atenta a sus comentarios | J88: DIFERENCIA EN INVENTARIO EN CUSTODIA | K88: SI | L88: MAYOR | M88: PRODUCCIÓN Y DIRECCIÓN TÉCNICA | N88: RICO GIL LEIDY BIBIANA | O88: 46113 | P88: 46113 | Q88: CERRADA | S88: ABIERTA | T88: SERVICIO AL CLIENTE | U88: Manuela González Lanzas Jefe técnico SDMDU HUSJ | V88: 3105474457 | W88: director.unidosis@husj.gov.co | X88: ADJUNTOS | Y88: NO
A89: 1 | B89: 85 | C89: 46097 | D89: MARZO | E89: CUNDINAMARCA | F89: FUNDACION ABOOD SHAIO | G89: FUND SHAIO | H89: ESTERILES | I89: Buenas noches, Durante la recepción técnica realizada el día de hoy se identificó una inconsistencia en el etiquetado de un preparado magistral, en la cual el nombre del medicamento consignado en la etiqueta exterior no correspondía al contenido real del preparado. La situación fue detectada debido a que se evidenció la ausencia de un magistral esperado y la duplicidad de una unidosis correspondiente a otro paciente. Al proceder a la apertura de las bolsas se encontró que: La etiqueta exterior correspondía a amiodarona del paciente O. Gai Pedraza. Sin embargo, en el interior se encontraba una jeringa etiquetada como furosemida correspondiente al paciente Gael Dariel Sabogal. Este evento representa un riesgo significativo para la seguridad del paciente, ya que se estaban intercambiando unidosis entre pacientes diferentes y con características clínicas distintas, específicamente entre: Paciente adulto: Amiodarona 200 mg Paciente pediátrico: Furosemida 4 mg Una situación de este tipo podría derivar en la administración de un medicamento incorrecto, en una dosis no indicada y a un paciente equivocado, con posibles consecuencias clínicas graves. Por lo anterior, solicitamos amablemente la revisión del caso y la implementación de un plan de mejora, con el fin de fortalecer los controles en los procesos de preparación, rotulación y verificación de magistrales, evitando así la recurrencia de este tipo de incidentes. Muchas gracias. | J89: DIFERENCIA EN INVENTARIO EN CUSTODIA | K89: SI | L89: MAYOR | M89: PRODUCCIÓN Y DIRECCIÓN TÉCNICA | N89: RICO GIL LEIDY BIBIANA | Q89: ABIERTA | S89: ABIERTA | T89: SERVICIO AL CLIENTE | U89: Oscar Alfonso Vargas Bautista Químico(a) Farmacéutico(a) | V89: PBX (601) 593 8210 | W89: alfonso.vargas@shaio.org | X89: ADJUNTOS | Y89: NO
A90: 1 | B90: 86 | C90: 46097 | D90: MARZO | E90: CUNDINAMARCA | F90: HOSPITAL UNIVERSITARIO SAN IGNACIO | G90: HOSPITAL UNIVERSITARIO SAN IGNACIO | H90: ESTERILES | I90: Cordial saludo El presente con el fin de reportar queja en cuanto al retraso en entrega de 16 dosis unitarias de estériles del día 16 de marzo (hora de envío OP 12:28) y fueron recibidas a las 17:47 (horario pactado 17:00). Adjunto envío documento. Agradezco la atención prestada al presente y quedo atenta. Atentamente Cordial saludo El presente con el fin de reportar queja en cuanto al retraso en entrega de 5 NPT pediátricas del servicio de extensión hospitalaria del día 16 de marzo (hora de envío OP 08:55) y fueron recibidas a las 17:45 (horario pactado 15:00). Adjunto envío documento. Agradezco la atención prestada al presente y quedo atenta. | J90: ENTREGA FUERA DEL ACUERDO DE SERVICIO | K90: SI | L90: MAYOR | M90: PRODUCCIÓN Y DIRECCIÓN TÉCNICA | N90: MARTIN DURANGO | Q90: ABIERTA | S90: ABIERTA | T90: SERVICIO AL CLIENTE | U90: Luisa Ovalle Químico Farmacéutico Asistencial | V90: Teléfono: (601) 5946161 Ext. 3007 | W90: dacaicedo@husi.org.co | X90: ADJUNTOS | Y90: NO
A91: 1 | B91: 87 | C91: 46097 | D91: MARZO | E91: CUNDINAMARCA | F91: FARMART | G91: FARMART | H91: SOLIDOS | I91: Buendía, Informo que, enla recepción dela unidosis correspondiente al mes de marzo, documento #04300, seevidenció que el medicamento DEXAMETASONA 4MG TABLETA (UNIDOSIS) 1 COLOMPACK I MYECORT 1 un idad llegó con un c abello en la parte del sellado del empaque. | J91: PRODUCTO NO CONFORME | K91: SI | L91: MAYOR | M91: PRODUCCIÓN Y DIRECCIÓN TÉCNICA | N91: DORIA NARVÁEZ REYES ENRIQUE | Q91: ABIERTA | S91: ABIERTA | T91: SERVICIO AL CLIENTE | U91: ANDREA CHANTRE CORDINADORA | V91: 3185578038 | W91: auxcontable1@farmartips.com | X91: ADJUNTOS | Y91: NO
A92: 1 | B92: 88 | C92: 46099 | D92: MARZO | E92: CUNDINAMARCA | F92: HOSPITAL UNIVERSITARIO SAN IGNACIO | G92: HOSPITAL UNIVERSITARIO SAN IGNACIO | H92: DOSIS ANTICIPADA | I92: Cordial saludo El presente con el fin de reportar queja en cuanto a entrega incompleta de las dosis unitarias de propofol de 150mg/15mL (OP generada el 13 de marzo a las 15:33 por 68 DU ) el día de ayer 17 marzo fueron recibidas sólo 18DU a las 7:55. Adjunto envío documento. . | J92: ENTREGA FUERA DEL ACUERDO DE SERVICIO | K92: SI | L92: MAYOR | M92: PRODUCCIÓN Y DIRECCIÓN TÉCNICA | N92: MARTIN DURANGO | Q92: ABIERTA | S92: ABIERTA | T92: SERVICIO AL CLIENTE | U92: Luisa Ovalle Químico Farmacéutico Asistencial | V92: Teléfono: (601) 5946161 Ext. 3007 | W92: luovalle@husi.org.co | X92: ADJUNTOS | Y92: NO
A93: 1 | B93: 89 | C93: 46099 | D93: MARZO | E93: CUNDINAMARCA | F93: FARMART | G93: FARMART | H93: SOLIDOS | I93: Buen día, De manera atenta me permito informar que, durante la recepción de la orden de producción correspondiente al mes de marzo, se evidenciaron las siguientes novedades y averías adicionales a las reportadas previamente por el proveedor en el documento No. 0432O: Medicamento LOTE VTO Cantidad novedad CALCITRIOL 0.50MCG CAPSULA COLMED 1578216 30-09-2027 1 AVERIA CARBONATO DE CALCIO 600MG TABLETA | SIEGFRIED 17010925 30-09-2028 1 AVERIA ACIDO ASCORBICO 500MG TABLETA | ECAR | VITAMINA C F080423 30-08-2027 1 AVERIA AMLODIPINO 10MG TABLETA | GENFAR | F02152D 30-09-2028 2 1 AVERIA 1 EMPAQUE VACIO, NO CONTIENE TABLETA CARVEDILOL 12.5MG TABLETA | GENFAR 115527 30-09-2027 2 1 EMPAQUE VACIO, NO CONTIENE TABLETA. 1 EMPAQUE CON 2 TABLETAS. CARVEDILOL 6.25MG TABLETA | GENFAR 104717 30-08-2027 12 1 AVERIA 11 FALTANTES, NO SE RECIBIERON FISICAMENTE. DAPAGLIFLOZINA 10MG TABLETA | ASTRA ZENECA | FORXIGA YH0168 28-02-2028 1 AVERIA PREGABALINA 75MG TABLETA | ECAR F100056 30-10-2027 4 AVERIAS QUETIAPINA 25MG TABLETA | HETERO LABS LIMITED| TIQUEPIN FD251406 28-02-2028 2 AVERIA RISPERIDONA 1MG TABLETA | LA SANTE | ZYRISP GA0702A 30-07-2027 1 AVERIA VALSARTAN 80MG TABLETA | GARMISCH | VALSAPREX S18576 30-10-2027 15 14 AVERIAS 1 EMPAQUE VACIO, NO CONTIENE TABLETA. VITAMINA D3 1000UI CAPSULA | COLMED | CAPSULA BLANDA 1577737 30-09-2027 1 AVERIA | J93: PRODUCTO NO CONFORME | K93: SI | L93: MAYOR | M93: PRODUCCIÓN Y DIRECCIÓN TÉCNICA | N93: DORIA NARVÁEZ REYES ENRIQUE | Q93: ABIERTA | S93: ABIERTA | T93: SERVICIO AL CLIENTE | U93: ANGIE PIRQUIVE | V93: 3168785821 | W93: auxmedicamentoshuv@farmartips.com | X93: ADJUNTOS | Y93: NO
A94: 1 | B94: 90 | C94: 46099 | D94: MARZO | E94: CUNDINAMARCA | F94: CHRISTUS SINERGIA | G94: PALMA REAL | H94: DOSIS ANTICIPADA | I94: Buen día, Espero se encuentren bien. De manera atenta me permito remitir formato de PQR adjunto, correspondiente al reclamo por fuga en preparaciones de Clindamicina asociadas a dosis anticipadas, presentadas los días 13 y 16 de marzo de 2026. Así mismo, se adjuntan los soportes correspondientes para su revisión. Agradecemos su gestión frente a la situación presentada y quedamos atentos a sus comentarios y acciones derivadas del caso. Cordialmente, | J94: PRODUCTO NO CONFORME | K94: SI | L94: MAYOR | M94: PRODUCCIÓN Y DIRECCIÓN TÉCNICA | N94: MARTIN DURANGO | Q94: ABIERTA | S94: ABIERTA | T94: SERVICIO AL CLIENTE | U94: ANDREA KATHERINE CAICEDO | V94: N/R | W94: quimicofarmaceutico1.cpr@christus.co | X94: ADJUNTOS | Y94: NO
A95: 1 | B95: 91 | C95: 46099 | D95: MARZO | E95: CUNDINAMARCA | F95: HOSPITAL UNIVERSITARIO SAN IGNACIO | G95: HOSPITAL UNIVERSITARIO SAN IGNACIO | H95: NPT | I95: Cordial saludo El presente con el fin de reportar queja en cuanto a condiciones de transporte de nutriciones parenterales del servicio de pediatría del 13 de marzo de 2026 (OP generada el 13 de marzo a las 10:02 por 5 nutriciones ) con registro de temperatura de 15.6°C. Adjunto envío documento. Agradezco la atención prestada. | J95: ERROR ALMACENAMIENTO/TRANSPORTE DE MEDICAMENTOS E INSUMOS | K95: SI | L95: MAYOR | M95: PRODUCCIÓN Y DIRECCIÓN TÉCNICA | N95: MARTIN DURANGO | Q95: ABIERTA | S95: ABIERTA | T95: SERVICIO AL CLIENTE | U95: Luisa Ovalle Químico Farmacéutico Asistencial | V95: Teléfono: (601) 5946161 Ext. 3007 | W95: luovalle@husi.org.co | X95: ADJUNTOS | Y95: NO
A96: 1 | B96: 92 | C96: 46099 | D96: MARZO | E96: CUNDINAMARCA | F96: HOSPITAL UNIVERSITARIO SAN IGNACIO | G96: HOSPITAL UNIVERSITARIO SAN IGNACIO | H96: NPT | I96: Cordial saludo El presente con el fin de reportar queja en cuanto a condiciones de transporte y horario de entrega de nutriciones parenterales del servicio de extensión hospitalaria del 13 de marzo de 2026 (OP generada el 13 de marzo a las 08:22 por 6 nutriciones) con registro de temperatura de 15.6°C y horario de entrega 16:45 (horario pactado 15:00) . Adjunto envío documento. Agradezco la atención prestada. | J96: ENTREGA FUERA DEL ACUERDO DE SERVICIO | K96: SI | L96: MAYOR | M96: PRODUCCIÓN Y DIRECCIÓN TÉCNICA | N96: MARTIN DURANGO | Q96: ABIERTA | S96: ABIERTA | T96: SERVICIO AL CLIENTE | U96: Luisa Ovalle Químico Farmacéutico Asistencial | V96: Teléfono: (601) 5946161 Ext. 3007 | W96: luovalle@husi.org.co | X96: ADJUNTOS | Y96: NO
A97: 1 | B97: 93 | C97: 46099 | D97: MARZO | E97: CUNDINAMARCA | F97: HOSPITAL UNIVERSITARIO SAN IGNACIO | G97: HOSPITAL UNIVERSITARIO SAN IGNACIO | H97: NPT | I97: Cordial saludo El presente con el fin de reportar queja en cuanto a condiciones de transporte de las DU de insulina cristalina 100 UI/mL del 13 de marzo de 2026 (OP generada el 13 de marzo a las 12:28 por 10 DU) con registro de temperatura de 16.2°C. Adjunto envío documento. Quedo atenta a cualquier inquietud. Cordialmente | J97: ERROR ALMACENAMIENTO/TRANSPORTE DE MEDICAMENTOS E INSUMOS | K97: SI | L97: MAYOR | M97: PRODUCCIÓN Y DIRECCIÓN TÉCNICA | N97: MARTIN DURANGO | Q97: ABIERTA | S97: ABIERTA | T97: SERVICIO AL CLIENTE | U97: Luisa Ovalle Químico Farmacéutico Asistencial | V97: Teléfono: (601) 5946161 Ext. 3007 | W97: luovalle@husi.org.co | X97: ADJUNTOS | Y97: NO
A98: 1 | B98: 94 | C98: 46099 | D98: MARZO | E98: CUNDINAMARCA | F98: ETICOS | G98: HOCEN | H98: NPT | I98: Asunto: Devolución y reposición de preparación de nutrición parenteral – Neonato-paciente hija de Karen Cerón Dussán, con identificación M-00035789 Estimados, Por medio del presente me permito informar que se envió a preparación la orden de producción de nutrición parenteral para el neonato, paciente hija de Karen Cerón Dussán, con identificación M-00035789, con un volumen de fórmula por día de 144 cc más 30 ml de purga, para un volumen final de 174 cc. Durante la recepción técnica de la preparación inicial, se evidenció que el volumen total entregado fue de 204 ml, mientras que el volumen solicitado correspondía a 174 ml, por lo cual se procedió a la devolución de la misma. Agradezco el apoyo del equipo de producción, quienes realizaron una nueva preparación conforme a la orden establecida, la cual fue recibida correctamente y cumple con el volumen solicitado. El presente correo se emite con el fin de dejar trazabilidad del evento y la respectiva gestión realizada. Se adjunta registro fotográfico como soporte de la verificación realizada durante la recepción técnica | J98: PRODUCTO NO CONFORME | K98: SI | L98: MAYOR | M98: PRODUCCIÓN Y DIRECCIÓN TÉCNICA | N98: MARTIN DURANGO | Q98: ABIERTA | S98: ABIERTA | T98: SERVICIO AL CLIENTE | U98: Esteban Rodriguez Químico Farmacéutico HOCEN | V98: N/R | W98: qf4farmacia13302001@eticos.com | X98: ADJUNTOS | Y98: NO
A99: 1 | B99: 95 | C99: 46100 | D99: MARZO | E99: OCCIDENTE | F99: CHRISTUS SINERGIA | G99: PALMA REAL | H99: NPT | I99: Cordial Saludo, Por medio de la presente me permito adjuntar el formato PQR, donde se da a conocer el retraso presentado en la entrega de adecuaciones del día 18/03/2026. Agradezco una respuesta oportuna para evitar la recurrencia de esta situación, y quedamos atentas a las acciones correspondientes al caso. Muchas gracias | J99: ENTREGA FUERA DEL ACUERDO DE SERVICIO | K99: SI | L99: MAYOR | M99: PRODUCCIÓN Y DIRECCIÓN TÉCNICA | N99: ANGELA MARCELA PARRA ESPITIA | Q99: ABIERTA | S99: ABIERTA | T99: SERVICIO AL CLIENTE | U99: ESTEFANIA MONTENEGRO QUIMICO FARMACEUTICO | V99: N/R | W99: quimicofarmaceutico3.cpr@christus.co | X99: ADJUNTOS | Y99: NO
A100: 1 | B100: 96 | C100: 46100 | D100: MARZO | E100: COSTA | F100: CLINICA BAHIA | G100: CLINICA BAHIA | H100: ESTERILES | I100: Buenas dias Sres. UNIDOSIS S.A,S cordial saludo. En el proceso de recepción técnica correspondiente a la orden generada el día 18/03/2026, se realizaron las siguientes solicitudes: Cefazolina 0.400 g , Habitacion 316A Cefazolina 0.400 g , Habitacion 316B Cefazolina 0.600 g , Habitacion 317A Durante la verificación de los productos recibidos, se evidenciaron las siguientes novedades: Se recibió la totalidad de las dosis en presentación de 2 g, las cuales no corresponden a lo solicitado. Total 9 Unidades. Adicionalmente, se evidenció la fuga de una unidosis de tramadol correspondiente a la habitación 207B. La presente situación se notifica debido al riesgo que representa para la seguridad del paciente, considerando que la no concordancia entre lo solicitado y lo entregado constituye una falla en el proceso. Especialmente en el contexto de dosis pediátricas, pudo haber ocasionado la generación de eventos adversos. Por lo anterior, se notifica con el fin de prevenir la recurrencia de este tipo de situaciones. image.png | J100: PRODUCTO NO CONFORME | K100: SI | L100: MAYOR | M100: PRODUCCIÓN Y DIRECCIÓN TÉCNICA | N100: MARTINEZ GRANADOS MARIA VICTORIA | Q100: ABIERTA | S100: ABIERTA | T100: SERVICIO AL CLIENTE | U100: Brenda Morales Quimico Farmaceutico | V100: N/R | W100: controlgasesmedicinales@clinicabahia.com | X100: ADJUNTOS | Y100: NO
...

Sheet OTROS
A1: REGIONAL | B1: LINEA | C1: CALSIFICACION | D1: TIPO DE SOLICITUD | E1: PROCESO | F1: TIPIFICACION | G1: MEDIO EN QUE ENVIA LA QUEJA | H1: PROCESOS RELACIONADO
A2: ANTIOQUIA | B2: ADMINISTRATIVO | C2: CRITICO | D2: FELICITACION | E2: GERENCIA GENERAL | F2: PRODUCTO NO CONFORME | G2: CARTA | H2: SERVICIO
A3: COSTA | B3: DOSIS ANTICIPADA | C3: MAYOR | D3: PREGUNTA | E3: PRODUCCIÓN Y DIRECCIÓN TÉCNICA | F3: NO CONFORMIDAD ENTRE LO SOLICITADO Y LO ENTREGADO | G3: IMAIL | H3: TECNICA
A4: CUNDINAMARCA | B4: ESTERILES | C4: MENOR | D4: QUEJA | E4: COMERCIAL | F4: REPORTE DE FARMACOVIGILANCIA | G4: OTRO
A5: EJE CAFETERO | B5: MAGISTRAL NO ESTERILES | C5: IMPRESINDIBLE | D5: RECLAMO | E5: OPERACIONES Y LOGÍSTICA | F5: DIFERENCIA EN INVENTARIO EN CUSTODIA | G5: PERSONAL
A6: LLANOS | B6: NPT | C6: IMPORTANTE | D6: SUGERENCIA | E6: ADMINISTRATIVA Y FINANCIERA | F6: ENTREGA FUERA DEL ACUERDO DE SERVICIO | G6: TELEFONO
A7: MARLY CUNDINAMARCA | B7: ONCOLOGÍA | C7: NORMAL | E7: TALENTO HUMANO | F7: ERROR ALMACENAMIENTO/TRANSPORTE DE MEDICAMENTOS E INSUMOS | G7: WEB
A8: OCCIDENTE | B8: SOLIDOS | E8: SEGURIDAD Y SALUD EN EL TRABAJO | F8: ERROR DE INTERPRETACIÓN
A9: SANTANDER | B9: TODAS | F9: ERROR DE EMBALAJE
A10: CUNDINAMARCA SOLIDOS | B10: LOGISTICA | E10: ASEGURAMIENTO DE CALIDAD | F10: ERROR DE EMPAQUE
A11: CUNDINAMARCA MAGISTRALES | B11: LOGISTICA (BLITZ) | F11: ERROR DE RE EMPAQUE
A12: BLITZ CELTA | F12: ERROR EN ETIQUETA/CODIFICADO
A13: BLITZ TOCANCIPA | F13: ERROR EN DESPACHO
A14: BLITZ ADMINISTRATIVA | F14: INCUMPLIMIENTO ACTIVIDADES O COMPROMISOS
A15: BLITZ OCCIDENTE | F15: SOLICITUD DE RESULTADOS MICROBIOLÓGICOS
A16: CUNDINAMARCA VETERINARIA | F16: SOLICITUD DEL CLIENTE

Sheet RESPONSABLE 
A1: RESPONSABLE | B1: CARGO
A2: ANDREA HERRERA | B2: DIRECTORA NACIONAL ADMINISTRATIVA
A3: TATIANA RICO | B3: DIRECTOR DE TECNICO REGIONA LLANOS
A4: IVAN PEREIRA | B4: DIRECTOR TECNICO REGIONAL SANTANDER
A5: CARMONA RIOS FRANCISCO JULIAN | B5: DIRECTOR DE CALIDAD REGIONAL ANTIOQUIA
A6: ESTEFANIA MARTINEZ MARTINEZ | B6: DIRECTOR DE CALIDAD REGIONAL COSTA
A7: DORIA NARVÁEZ REYES ENRIQUE | B7: COORDINADOR PRODUCCION PLANTA SOLIDOS NO ESTERILES BOGOTA
A8: DIANA M MUÑOZ M | B8: DIRECTOR DE ASEGURAMIENTO DE CALIDAD NACIONAL
A9: FLOR DE LIZ PINEDA | B9: ANALISTA DE GESTION DE CALIDAD NACIONAL
A10: FRANCISCO ALVAREZ | B10: DIRECTOR TECNICO NACIONAL
A11: CHIRINOS MAESTRE MARY YOHELIN | B11: DIRECTOR DE CALIDAD REGIONAL MARLY
A12: GRANADA ESTRADA HERMES JAMES | B12: DIRECTOR TECNICO REGIONAL ANTIOQUIA
... A29: MANUEL GASCA | B29: Director comercial Zona Occidente
